Workbook
Name tx_Since: 'Final Project Dataset'!$M$2:$M$251
Name tx_Price: 'Final Project Dataset'!$I$2:$I$251
Name tx_ProdID: 'Final Project Dataset'!$E$2:$E$251
Name tx_Total: 'Final Project Dataset'!$N$2:$N$251
Name tx_Segment: 'Final Project Dataset'!$L$2:$L$251
Name tx_Region: 'Final Project Dataset'!$K$2:$K$251
Name tx_Qty: 'Final Project Dataset'!$H$2:$H$251
Name tx_CustName: 'Final Project Dataset'!$D$2:$D$251
Name tx_Product: 'Final Project Dataset'!$F$2:$F$251
Name tx_Category: 'Final Project Dataset'!$G$2:$G$251
Name tx_Pay: 'Final Project Dataset'!$J$2:$J$251
Name tx_Date: 'Final Project Dataset'!$B$2:$B$251
Name tx_CustID: 'Final Project Dataset'!$C$2:$C$251
Name tx_ID: 'Final Project Dataset'!$A$2:$A$251

Sheet Project Instructions
A1: PR. Final Project - "Data Intelligence Dashboard"
A2: Dataset: Use the 'Final Project Dataset' sheet containing 200+ records of customer transactions. Objective: Create a full-fledged analysis and reporting solution using Excel to analyze customer transactions, find insights, and build visualizations and dashboards. Key Topics to Implement: - Date & Time Functions: TODAY, NOW, DATEDIF, EOMONTH - FILTER Function for multi-value returns - Conditional Formatting with Icons/Arrows - Create Timestamp (using NOW and iterative calculations) - WHAT-IF Analysis: Scenario Manager, Goal Seek - Linear Regression using Data Analysis Toolpak - Data Analysis & Storytelling from the dataset - Use GroupBy concepts to find High-Value Customers using formulas - Create Dashboard using: - Pivot Tables - Pivot Charts (Bar, Line, Pie) - Slicers and Timelines - KPI Indicators with Conditional Formatting - Find most frequently purchased product or repeating names using formulas - Compare two lists and extract matching names in a new column - Create Abbreviations using TEXT functions - Build a final report with insights and storytelling Deliverable: - Well-structured workbook with multiple sheets (Raw Data, Analysis, Visualizations, Dashboard) - Summary Insights with key metrics: Total Revenue, Top Customers, Most Sold Products, Regional Sales - Use of all required formulas and functions as listed above

Sheet Final Project Dataset
A1: Transaction_ID | B1: Date | C1: Customer_ID | D1: Customer_Name | E1: Product_ID | F1: Product_Name | G1: Category | H1: Quantity | I1: Unit_Price | J1: Payment_Method | K1: Region | L1: Customer_Segment | M1: Customer_Since | N1: Total_Amount
A2: TRX0155 | B2: 45393 | C2: CUST023 | D2: Paul Baker | E2: P009 | F2: Monitor | G2: Electronics | H2: 3 | I2: 249.99 | J2: Cash | K2: Central | L2: Basic | M2: 44425 | N2: 749.97
A3: TRX0023 | B3: 45396 | C3: CUST013 | D3: Joseph Jackson | E3: P009 | F3: Monitor | G3: Electronics | H3: 3 | I3: 249.99 | J3: Credit Card | K3: Central | L3: Premium | M3: 44575 | N3: 749.97
A4: TRX0139 | B4: 45399 | C4: CUST021 | D4: Kevin Scott | E4: P005 | F4: Blender | G4: Appliances | H4: 3 | I4: 59.99 | J4: PayPal | K4: South | L4: Standard | M4: 45262 | N4: 179.97
A5: TRX0043 | B5: 45400 | C5: CUST046 | D5: Kathleen Bennett | E5: P005 | F5: Blender | G5: Appliances | H5: 3 | I5: 59.99 | J5: Cash | K5: North | L5: Premium | M5: 45114 | N5: 179.97
A6: TRX0212 | B6: 45400 | C6: CUST003 | D6: Michael Brown | E6: P008 | F6: Bookshelf | G6: Furniture | H6: 5 | I6: 149.99 | J6: Credit Card | K6: North | L6: Premium | M6: 45295 | N6: 749.95
A7: TRX0092 | B7: 45403 | C7: CUST024 | D7: Dorothy Nelson | E7: P005 | F7: Blender | G7: Appliances | H7: 2 | I7: 59.99 | J7: Cash | K7: West | L7: Standard | M7: 44746 | N7: 119.98
A8: TRX0193 | B8: 45403 | C8: CUST024 | D8: Dorothy Nelson | E8: P003 | F8: Headphones | G8: Electronics | H8: 5 | I8: 149.99 | J8: Credit Card | K8: Central | L8: Standard | M8: 44418 | N8: 749.95
A9: TRX0240 | B9: 45403 | C9: CUST017 | D9: Charles Allen | E9: P005 | F9: Blender | G9: Appliances | H9: 3 | I9: 59.99 | J9: Debit Card | K9: South | L9: Basic | M9: 45007 | N9: 179.97
A10: TRX0135 | B10: 45405 | C10: CUST009 | D10: Robert Thomas | E10: P001 | F10: Laptop | G10: Electronics | H10: 3 | I10: 899.99 | J10: PayPal | K10: East | L10: Standard | M10: 45299 | N10: 2699.97
A11: TRX0185 | B11: 45408 | C11: CUST026 | D11: Karen Hill | E11: P005 | F11: Blender | G11: Appliances | H11: 3 | I11: 59.99 | J11: Cash | K11: West | L11: Premium | M11: 45207 | N11: 179.97
A12: TRX0138 | B12: 45408 | C12: CUST022 | D12: Susan Green | E12: P008 | F12: Bookshelf | G12: Furniture | H12: 1 | I12: 149.99 | J12: Credit Card | K12: West | L12: Standard | M12: 45103 | N12: 149.99
A13: TRX0209 | B13: 45408 | C13: CUST046 | D13: Kathleen Bennett | E13: P008 | F13: Bookshelf | G13: Furniture | H13: 5 | I13: 149.99 | J13: Debit Card | K13: North | L13: Basic | M13: 44830 | N13: 749.95
... A251: TRX0064 | B251: 45758 | C251: CUST031 | D251: Steven Turner | E251: P010 | F251: Keyboard | G251: Electronics | H251: 3 | I251: 89.99 | J251: Debit Card | K251: North | L251: Premium | M251: 44878 | N251: 269.97

Sheet Lists
A3: Region | B3: Category | C3: Product_ID | D3: Product_Name | E3: Payment_Method | F3: Customer_Segment | G3: Customer_ID | H3: Customer_Name | I3: ALL Region | J3: ALL Category
A4: Central | B4: Appliances | C4: P001 | D4: Laptop | E4: Cash | F4: Basic | G4: CUST001 | H4: {=INDEX(tx_CustName,MATCH(G4,tx_CustID,0))} -> John Smith | I4: All | J4: All
A5: East | B5: Electronics | C5: P002 | D5: Smartphone | E5: Credit Card | F5: Premium | G5: CUST002 | H5: {=INDEX(tx_CustName,MATCH(G5,tx_CustID,0))} -> Emma Wilson | I5: Central | J5: Appliances
A6: North | B6: Furniture | C6: P003 | D6: Headphones | E6: Debit Card | F6: Standard | G6: CUST003 | H6: {=INDEX(tx_CustName,MATCH(G6,tx_CustID,0))} -> Michael Brown | I6: East | J6: Electronics
A7: South | C7: P004 | D7: Coffee Maker | E7: PayPal | G7: CUST004 | H7: {=INDEX(tx_CustName,MATCH(G7,tx_CustID,0))} -> Sarah Davis | I7: North | J7: Furniture
A8: West | C8: P005 | D8: Blender | G8: CUST005 | H8: {=INDEX(tx_CustName,MATCH(G8,tx_CustID,0))} -> James Johnson | I8: South
C9: P006 | D9: Office Chair | G9: CUST006 | H9: {=INDEX(tx_CustName,MATCH(G9,tx_CustID,0))} -> Lisa Anderson | I9: West
C10: P007 | D10: Desk | G10: CUST007 | H10: {=INDEX(tx_CustName,MATCH(G10,tx_CustID,0))} -> David Martinez
C11: P008 | D11: Bookshelf | G11: CUST008 | H11: {=INDEX(tx_CustName,MATCH(G11,tx_CustID,0))} -> Jennifer Taylor
C12: P009 | D12: Monitor | G12: CUST009 | H12: {=INDEX(tx_CustName,MATCH(G12,tx_CustID,0))} -> Robert Thomas
C13: P010 | D13: Keyboard | G13: CUST010 | H13: {=INDEX(tx_CustName,MATCH(G13,tx_CustID,0))} -> Maria Garcia
G14: CUST011 | H14: {=INDEX(tx_CustName,MATCH(G14,tx_CustID,0))} -> William White
G15: CUST012 | H15: {=INDEX(tx_CustName,MATCH(G15,tx_CustID,0))} -> Patricia Moore
G16: CUST013 | H16: {=INDEX(tx_CustName,MATCH(G16,tx_CustID,0))} -> Joseph Jackson
G17: CUST014 | H17: {=INDEX(tx_CustName,MATCH(G17,tx_CustID,0))} -> Linda Martin
G18: CUST015 | H18: {=INDEX(tx_CustName,MATCH(G18,tx_CustID,0))} -> Richard Lee
G19: CUST016 | H19: {=INDEX(tx_CustName,MATCH(G19,tx_CustID,0))} -> Elizabeth Hall
G20: CUST017 | H20: {=INDEX(tx_CustName,MATCH(G20,tx_CustID,0))} -> Charles Allen
G21: CUST018 | H21: {=INDEX(tx_CustName,MATCH(G21,tx_CustID,0))} -> Barbara Young
G22: CUST019 | H22: {=INDEX(tx_CustName,MATCH(G22,tx_CustID,0))} -> Daniel King
G23: CUST020 | H23: {=INDEX(tx_CustName,MATCH(G23,tx_CustID,0))} -> Margaret Wright
G24: CUST021 | H24: {=INDEX(tx_CustName,MATCH(G24,tx_CustID,0))} -> Kevin Scott
G25: CUST022 | H25: {=INDEX(tx_CustName,MATCH(G25,tx_CustID,0))} -> Susan Green
... G53: CUST050 | H53: {=INDEX(tx_CustName,MATCH(G53,tx_CustID,0))} -> Julie Foster

Sheet Date_Time
A1: Live date functions
A2: Item | B2: Result | E2: Customer_ID | F2: Customer_Name | G2: First Purchase | H2: Last Purchase | I2: Customer Since (earliest) | J2: Tenure (full years) | K2: Tenure (extra months) | L2: Days Since Last Purchase | M2: Tenure (text)
A3: TODAY() | B3: =TODAY() -> 46295 | E3: =Lists!G4 -> CUST001 | F3: =Lists!H4 -> John Smith | G3: =MINIFS(tx_Date,tx_CustID,$E3) -> 45740 | H3: =MAXIFS(tx_Date,tx_CustID,$E3) -> 45740 | I3: =MINIFS(tx_Since,tx_CustID,$E3) -> 44560 | J3: =DATEDIF(I3,TODAY(),"Y") -> 4 | K3: =DATEDIF(I3,TODAY(),"YM") -> 9 | L3: =TODAY()-H3 -> 555 | M3: =J3&"y "&K3&"m" -> 4y 9m
A4: NOW() | B4: =NOW() -> 46295.989 | E4: =Lists!G5 -> CUST002 | F4: =Lists!H5 -> Emma Wilson | G4: =MINIFS(tx_Date,tx_CustID,$E4) -> 45430 | H4: =MAXIFS(tx_Date,tx_CustID,$E4) -> 45737 | I4: =MINIFS(tx_Since,tx_CustID,$E4) -> 44748 | J4: =DATEDIF(I4,TODAY(),"Y") -> 4 | K4: =DATEDIF(I4,TODAY(),"YM") -> 2 | L4: =TODAY()-H4 -> 558 | M4: =J4&"y "&K4&"m" -> 4y 2m
A5: First transaction date | B5: =MIN(tx_Date) -> 45393 | E5: =Lists!G6 -> CUST003 | F5: =Lists!H6 -> Michael Brown | G5: =MINIFS(tx_Date,tx_CustID,$E5) -> 45400 | H5: =MAXIFS(tx_Date,tx_CustID,$E5) -> 45707 | I5: =MINIFS(tx_Since,tx_CustID,$E5) -> 44422 | J5: =DATEDIF(I5,TODAY(),"Y") -> 5 | K5: =DATEDIF(I5,TODAY(),"YM") -> 1 | L5: =TODAY()-H5 -> 588 | M5: =J5&"y "&K5&"m" -> 5y 1m
A6: Last transaction date | B6: =MAX(tx_Date) -> 45758 | E6: =Lists!G7 -> CUST004 | F6: =Lists!H7 -> Sarah Davis | G6: =MINIFS(tx_Date,tx_CustID,$E6) -> 45446 | H6: =MAXIFS(tx_Date,tx_CustID,$E6) -> 45619 | I6: =MINIFS(tx_Since,tx_CustID,$E6) -> 44458 | J6: =DATEDIF(I6,TODAY(),"Y") -> 5 | K6: =DATEDIF(I6,TODAY(),"YM") -> 0 | L6: =TODAY()-H6 -> 676 | M6: =J6&"y "&K6&"m" -> 5y 0m
A7: Dataset span (DATEDIF) | B7: =DATEDIF(B5,B6,"M")&" months, "&DATEDIF(B5,B6,"MD")&" days" -> 12 months, 0 days | E7: =Lists!G8 -> CUST005 | F7: =Lists!H8 -> James Johnson | G7: =MINIFS(tx_Date,tx_CustID,$E7) -> 45635 | H7: =MAXIFS(tx_Date,tx_CustID,$E7) -> 45635 | I7: =MINIFS(tx_Since,tx_CustID,$E7) -> 45052 | J7: =DATEDIF(I7,TODAY(),"Y") -> 3 | K7: =DATEDIF(I7,TODAY(),"YM") -> 4 | L7: =TODAY()-H7 -> 660 | M7: =J7&"y "&K7&"m" -> 3y 4m
A8: Days since last transaction | B8: =TODAY()-B6 -> 537 | E8: =Lists!G9 -> CUST006 | F8: =Lists!H9 -> Lisa Anderson | G8: =MINIFS(tx_Date,tx_CustID,$E8) -> 45428 | H8: =MAXIFS(tx_Date,tx_CustID,$E8) -> 45676 | I8: =MINIFS(tx_Since,tx_CustID,$E8) -> 44579 | J8: =DATEDIF(I8,TODAY(),"Y") -> 4 | K8: =DATEDIF(I8,TODAY(),"YM") -> 8 | L8: =TODAY()-H8 -> 619 | M8: =J8&"y "&K8&"m" -> 4y 8m
A9: End of current month (EOMONTH) | B9: =EOMONTH(TODAY(),0) -> 46295 | E9: =Lists!G10 -> CUST007 | F9: =Lists!H10 -> David Martinez | G9: =MINIFS(tx_Date,tx_CustID,$E9) -> 45476 | H9: =MAXIFS(tx_Date,tx_CustID,$E9) -> 45648 | I9: =MINIFS(tx_Since,tx_CustID,$E9) -> 44522 | J9: =DATEDIF(I9,TODAY(),"Y") -> 4 | K9: =DATEDIF(I9,TODAY(),"YM") -> 10 | L9: =TODAY()-H9 -> 647 | M9: =J9&"y "&K9&"m" -> 4y 10m
A10: Days left in current month | B10: =EOMONTH(TODAY(),0)-TODAY() -> 0 | E10: =Lists!G11 -> CUST008 | F10: =Lists!H11 -> Jennifer Taylor | G10: =MINIFS(tx_Date,tx_CustID,$E10) -> 45440 | H10: =MAXIFS(tx_Date,tx_CustID,$E10) -> 45635 | I10: =MINIFS(tx_Since,tx_CustID,$E10) -> 44407 | J10: =DATEDIF(I10,TODAY(),"Y") -> 5 | K10: =DATEDIF(I10,TODAY(),"YM") -> 2 | L10: =TODAY()-H10 -> 660 | M10: =J10&"y "&K10&"m" -> 5y 2m
A11: End of current quarter | B11: =EOMONTH(DATE(YEAR(TODAY()),CEILING(MONTH(TODAY()),3),1),0) -> 46295 | E11: =Lists!G12 -> CUST009 | F11: =Lists!H12 -> Robert Thomas | G11: =MINIFS(tx_Date,tx_CustID,$E11) -> 45405 | H11: =MAXIFS(tx_Date,tx_CustID,$E11) -> 45756 | I11: =MINIFS(tx_Since,tx_CustID,$E11) -> 44395 | J11: =DATEDIF(I11,TODAY(),"Y") -> 5 | K11: =DATEDIF(I11,TODAY(),"YM") -> 2 | L11: =TODAY()-H11 -> 539 | M11: =J11&"y "&K11&"m" -> 5y 2m
A12: Same day next year (EDATE) | B12: =EDATE(TODAY(),12) -> 46660 | E12: =Lists!G13 -> CUST010 | F12: =Lists!H13 -> Maria Garcia | G12: =MINIFS(tx_Date,tx_CustID,$E12) -> 45410 | H12: =MAXIFS(tx_Date,tx_CustID,$E12) -> 45604 | I12: =MINIFS(tx_Since,tx_CustID,$E12) -> 44579 | J12: =DATEDIF(I12,TODAY(),"Y") -> 4 | K12: =DATEDIF(I12,TODAY(),"YM") -> 8 | L12: =TODAY()-H12 -> 691 | M12: =J12&"y "&K12&"m" -> 4y 8m
A13: Last full month in data ends | B13: =EOMONTH(B6,-1) -> 45747 | E13: =Lists!G14 -> CUST011 | F13: =Lists!H14 -> William White | G13: =MINIFS(tx_Date,tx_CustID,$E13) -> 45554 | H13: =MAXIFS(tx_Date,tx_CustID,$E13) -> 45686 | I13: =MINIFS(tx_Since,tx_CustID,$E13) -> 44482 | J13: =DATEDIF(I13,TODAY(),"Y") -> 4 | K13: =DATEDIF(I13,TODAY(),"YM") -> 11 | L13: =TODAY()-H13 -> 609 | M13: =J13&"y "&K13&"m" -> 4y 11m
E14: =Lists!G15 -> CUST012 | F14: =Lists!H15 -> Patricia Moore | G14: =MINIFS(tx_Date,tx_CustID,$E14) -> 45413 | H14: =MAXIFS(tx_Date,tx_CustID,$E14) -> 45607 | I14: =MINIFS(tx_Since,tx_CustID,$E14) -> 44409 | J14: =DATEDIF(I14,TODAY(),"Y") -> 5 | K14: =DATEDIF(I14,TODAY(),"YM") -> 1 | L14: =TODAY()-H14 -> 688 | M14: =J14&"y "&K14&"m" -> 5y 1m
E15: =Lists!G16 -> CUST013 | F15: =Lists!H16 -> Joseph Jackson | G15: =MINIFS(tx_Date,tx_CustID,$E15) -> 45396 | H15: =MAXIFS(tx_Date,tx_CustID,$E15) -> 45627 | I15: =MINIFS(tx_Since,tx_CustID,$E15) -> 44475 | J15: =DATEDIF(I15,TODAY(),"Y") -> 4 | K15: =DATEDIF(I15,TODAY(),"YM") -> 11 | L15: =TODAY()-H15 -> 668 | M15: =J15&"y "&K15&"m" -> 4y 11m
E16: =Lists!G17 -> CUST014 | F16: =Lists!H17 -> Linda Martin | G16: =MINIFS(tx_Date,tx_CustID,$E16) -> 45424 | H16: =MAXIFS(tx_Date,tx_CustID,$E16) -> 45648 | I16: =MINIFS(tx_Since,tx_CustID,$E16) -> 44886 | J16: =DATEDIF(I16,TODAY(),"Y") -> 3 | K16: =DATEDIF(I16,TODAY(),"YM") -> 10 | L16: =TODAY()-H16 -> 647 | M16: =J16&"y "&K16&"m" -> 3y 10m
E17: =Lists!G18 -> CUST015 | F17: =Lists!H18 -> Richard Lee | G17: =MINIFS(tx_Date,tx_CustID,$E17) -> 45564 | H17: =MAXIFS(tx_Date,tx_CustID,$E17) -> 45715 | I17: =MINIFS(tx_Since,tx_CustID,$E17) -> 44728 | J17: =DATEDIF(I17,TODAY(),"Y") -> 4 | K17: =DATEDIF(I17,TODAY(),"YM") -> 3 | L17: =TODAY()-H17 -> 580 | M17: =J17&"y "&K17&"m" -> 4y 3m
E18: =Lists!G19 -> CUST016 | F18: =Lists!H19 -> Elizabeth Hall | G18: =MINIFS(tx_Date,tx_CustID,$E18) -> 45509 | H18: =MAXIFS(tx_Date,tx_CustID,$E18) -> 45711 | I18: =MINIFS(tx_Since,tx_CustID,$E18) -> 44431 | J18: =DATEDIF(I18,TODAY(),"Y") -> 5 | K18: =DATEDIF(I18,TODAY(),"YM") -> 1 | L18: =TODAY()-H18 -> 584 | M18: =J18&"y "&K18&"m" -> 5y 1m
E19: =Lists!G20 -> CUST017 | F19: =Lists!H20 -> Charles Allen | G19: =MINIFS(tx_Date,tx_CustID,$E19) -> 45403 | H19: =MAXIFS(tx_Date,tx_CustID,$E19) -> 45724 | I19: =MINIFS(tx_Since,tx_CustID,$E19) -> 44412 | J19: =DATEDIF(I19,TODAY(),"Y") -> 5 | K19: =DATEDIF(I19,TODAY(),"YM") -> 1 | L19: =TODAY()-H19 -> 571 | M19: =J19&"y "&K19&"m" -> 5y 1m
E20: =Lists!G21 -> CUST018 | F20: =Lists!H21 -> Barbara Young | G20: =MINIFS(tx_Date,tx_CustID,$E20) -> 45412 | H20: =MAXIFS(tx_Date,tx_CustID,$E20) -> 45708 | I20: =MINIFS(tx_Since,tx_CustID,$E20) -> 44613 | J20: =DATEDIF(I20,TODAY(),"Y") -> 4 | K20: =DATEDIF(I20,TODAY(),"YM") -> 7 | L20: =TODAY()-H20 -> 587 | M20: =J20&"y "&K20&"m" -> 4y 7m
E21: =Lists!G22 -> CUST019 | F21: =Lists!H22 -> Daniel King | G21: =MINIFS(tx_Date,tx_CustID,$E21) -> 45443 | H21: =MAXIFS(tx_Date,tx_CustID,$E21) -> 45660 | I21: =MINIFS(tx_Since,tx_CustID,$E21) -> 44446 | J21: =DATEDIF(I21,TODAY(),"Y") -> 5 | K21: =DATEDIF(I21,TODAY(),"YM") -> 0 | L21: =TODAY()-H21 -> 635 | M21: =J21&"y "&K21&"m" -> 5y 0m
E22: =Lists!G23 -> CUST020 | F22: =Lists!H23 -> Margaret Wright | G22: =MINIFS(tx_Date,tx_CustID,$E22) -> 45481 | H22: =MAXIFS(tx_Date,tx_CustID,$E22) -> 45745 | I22: =MINIFS(tx_Since,tx_CustID,$E22) -> 44421 | J22: =DATEDIF(I22,TODAY(),"Y") -> 5 | K22: =DATEDIF(I22,TODAY(),"YM") -> 1 | L22: =TODAY()-H22 -> 550 | M22: =J22&"y "&K22&"m" -> 5y 1m
E23: =Lists!G24 -> CUST021 | F23: =Lists!H24 -> Kevin Scott | G23: =MINIFS(tx_Date,tx_CustID,$E23) -> 45399 | H23: =MAXIFS(tx_Date,tx_CustID,$E23) -> 45704 | I23: =MINIFS(tx_Since,tx_CustID,$E23) -> 44578 | J23: =DATEDIF(I23,TODAY(),"Y") -> 4 | K23: =DATEDIF(I23,TODAY(),"YM") -> 8 | L23: =TODAY()-H23 -> 591 | M23: =J23&"y "&K23&"m" -> 4y 8m
E24: =Lists!G25 -> CUST022 | F24: =Lists!H25 -> Susan Green | G24: =MINIFS(tx_Date,tx_CustID,$E24) -> 45408 | H24: =MAXIFS(tx_Date,tx_CustID,$E24) -> 45682 | I24: =MINIFS(tx_Since,tx_CustID,$E24) -> 44564 | J24: =DATEDIF(I24,TODAY(),"Y") -> 4 | K24: =DATEDIF(I24,TODAY(),"YM") -> 8 | L24: =TODAY()-H24 -> 613 | M24: =J24&"y "&K24&"m" -> 4y 8m
E25: =Lists!G26 -> CUST023 | F25: =Lists!H26 -> Paul Baker | G25: =MINIFS(tx_Date,tx_CustID,$E25) -> 45393 | H25: =MAXIFS(tx_Date,tx_CustID,$E25) -> 45739 | I25: =MINIFS(tx_Since,tx_CustID,$E25) -> 44425 | J25: =DATEDIF(I25,TODAY(),"Y") -> 5 | K25: =DATEDIF(I25,TODAY(),"YM") -> 1 | L25: =TODAY()-H25 -> 556 | M25: =J25&"y "&K25&"m" -> 5y 1m
... E52: =Lists!G53 -> CUST050 | F52: =Lists!H53 -> Julie Foster | G52: =MINIFS(tx_Date,tx_CustID,$E52) -> 45452 | H52: =MAXIFS(tx_Date,tx_CustID,$E52) -> 45452 | I52: =MINIFS(tx_Since,tx_CustID,$E52) -> 44435 | J52: =DATEDIF(I52,TODAY(),"Y") -> 5 | K52: =DATEDIF(I52,TODAY(),"YM") -> 1 | L52: =TODAY()-H52 -> 843 | M52: =J52&"y "&K52&"m" -> 5y 1m

Sheet Customer_Analysis
A3: High-Value percentile | B3: 0.8 | D3: High-Value threshold ($) | E3: =PERCENTILE($E$8:$E$57,B3) -> 6557.8
A4: Mid-Value percentile | B4: 0.5 | D4: Mid-Value threshold ($) | E4: =PERCENTILE($E$8:$E$57,B4) -> 4254.875
N6: Top 10 Customers by Revenue
A7: Customer_ID | B7: Customer_Name | C7: Transactions | D7: Units | E7: Revenue | F7: Avg Order Value | G7: % of Total Revenue | H7: Rank | I7: Tier | J7: Repeat? | K7: Times Name Appears | L7: Last Purchase | N7: Rank | O7: Customer | P7: Revenue | Q7: Share | R7: Transactions | S7: Tier
A8: =Lists!G4 -> CUST001 | B8: =Lists!H4 -> John Smith | C8: =COUNTIF(tx_CustID,$A8) -> 1 | D8: =SUMIF(tx_CustID,$A8,tx_Qty) -> 4 | E8: =SUMIF(tx_CustID,$A8,tx_Total) -> 599.96 | F8: =IF(C8=0,0,E8/C8) -> 599.96 | G8: =E8/$E$58 -> 0.0026177125 | H8: =RANK(E8,$E$8:$E$57,0)+COUNTIF($E$8:E8,E8)-1 -> 47 | I8: =IF(E8>=$E$3,"High-Value",IF(E8>=$E$4,"Mid-Value","Low-Value")) -> Low-Value | J8: =IF(C8>1,"Repeat","One-time") -> One-time | K8: =COUNTIF(tx_CustName,$B8) -> 1 | L8: =MAXIFS(tx_Date,tx_CustID,$A8) -> 45740 | N8: 1 | O8: =INDEX($B$8:$B$57,MATCH($N8,$H$8:$H$57,0)) -> Mark Carter | P8: =INDEX($E$8:$E$57,MATCH($N8,$H$8:$H$57,0)) -> 15659.65 | Q8: =P8/$E$58 -> 0.068325325 | R8: =INDEX($C$8:$C$57,MATCH($N8,$H$8:$H$57,0)) -> 12 | S8: =INDEX($I$8:$I$57,MATCH($N8,$H$8:$H$57,0)) -> High-Value
A9: =Lists!G5 -> CUST002 | B9: =Lists!H5 -> Emma Wilson | C9: =COUNTIF(tx_CustID,$A9) -> 5 | D9: =SUMIF(tx_CustID,$A9,tx_Qty) -> 12 | E9: =SUMIF(tx_CustID,$A9,tx_Total) -> 1229.88 | F9: =IF(C9=0,0,E9/C9) -> 245.976 | G9: =E9/$E$58 -> 0.0053661449 | H9: =RANK(E9,$E$8:$E$57,0)+COUNTIF($E$8:E9,E9)-1 -> 44 | I9: =IF(E9>=$E$3,"High-Value",IF(E9>=$E$4,"Mid-Value","Low-Value")) -> Low-Value | J9: =IF(C9>1,"Repeat","One-time") -> Repeat | K9: =COUNTIF(tx_CustName,$B9) -> 5 | L9: =MAXIFS(tx_Date,tx_CustID,$A9) -> 45737 | N9: 2 | O9: =INDEX($B$8:$B$57,MATCH($N9,$H$8:$H$57,0)) -> Edward Mitchell | P9: =INDEX($E$8:$E$57,MATCH($N9,$H$8:$H$57,0)) -> 11919.77 | Q9: =P9/$E$58 -> 0.052007686 | R9: =INDEX($C$8:$C$57,MATCH($N9,$H$8:$H$57,0)) -> 6 | S9: =INDEX($I$8:$I$57,MATCH($N9,$H$8:$H$57,0)) -> High-Value
A10: =Lists!G6 -> CUST003 | B10: =Lists!H6 -> Michael Brown | C10: =COUNTIF(tx_CustID,$A10) -> 9 | D10: =SUMIF(tx_CustID,$A10,tx_Qty) -> 26 | E10: =SUMIF(tx_CustID,$A10,tx_Total) -> 6169.74 | F10: =IF(C10=0,0,E10/C10) -> 685.52667 | G10: =E10/$E$58 -> 0.026919471 | H10: =RANK(E10,$E$8:$E$57,0)+COUNTIF($E$8:E10,E10)-1 -> 14 | I10: =IF(E10>=$E$3,"High-Value",IF(E10>=$E$4,"Mid-Value","Low-Value")) -> Mid-Value | J10: =IF(C10>1,"Repeat","One-time") -> Repeat | K10: =COUNTIF(tx_CustName,$B10) -> 9 | L10: =MAXIFS(tx_Date,tx_CustID,$A10) -> 45707 | N10: 3 | O10: =INDEX($B$8:$B$57,MATCH($N10,$H$8:$H$57,0)) -> Barbara Young | P10: =INDEX($E$8:$E$57,MATCH($N10,$H$8:$H$57,0)) -> 10649.8 | Q10: =P10/$E$58 -> 0.046466623 | R10: =INDEX($C$8:$C$57,MATCH($N10,$H$8:$H$57,0)) -> 5 | S10: =INDEX($I$8:$I$57,MATCH($N10,$H$8:$H$57,0)) -> High-Value
A11: =Lists!G7 -> CUST004 | B11: =Lists!H7 -> Sarah Davis | C11: =COUNTIF(tx_CustID,$A11) -> 5 | D11: =SUMIF(tx_CustID,$A11,tx_Qty) -> 19 | E11: =SUMIF(tx_CustID,$A11,tx_Total) -> 5499.81 | F11: =IF(C11=0,0,E11/C11) -> 1099.962 | G11: =E11/$E$58 -> 0.023996469 | H11: =RANK(E11,$E$8:$E$57,0)+COUNTIF($E$8:E11,E11)-1 -> 19 | I11: =IF(E11>=$E$3,"High-Value",IF(E11>=$E$4,"Mid-Value","Low-Value")) -> Mid-Value | J11: =IF(C11>1,"Repeat","One-time") -> Repeat | K11: =COUNTIF(tx_CustName,$B11) -> 5 | L11: =MAXIFS(tx_Date,tx_CustID,$A11) -> 45619 | N11: 4 | O11: =INDEX($B$8:$B$57,MATCH($N11,$H$8:$H$57,0)) -> Patricia Moore | P11: =INDEX($E$8:$E$57,MATCH($N11,$H$8:$H$57,0)) -> 9799.73 | Q11: =P11/$E$58 -> 0.042757644 | R11: =INDEX($C$8:$C$57,MATCH($N11,$H$8:$H$57,0)) -> 8 | S11: =INDEX($I$8:$I$57,MATCH($N11,$H$8:$H$57,0)) -> High-Value
A12: =Lists!G8 -> CUST005 | B12: =Lists!H8 -> James Johnson | C12: =COUNTIF(tx_CustID,$A12) -> 1 | D12: =SUMIF(tx_CustID,$A12,tx_Qty) -> 3 | E12: =SUMIF(tx_CustID,$A12,tx_Total) -> 179.97 | F12: =IF(C12=0,0,E12/C12) -> 179.97 | G12: =E12/$E$58 -> 0.00078523522 | H12: =RANK(E12,$E$8:$E$57,0)+COUNTIF($E$8:E12,E12)-1 -> 50 | I12: =IF(E12>=$E$3,"High-Value",IF(E12>=$E$4,"Mid-Value","Low-Value")) -> Low-Value | J12: =IF(C12>1,"Repeat","One-time") -> One-time | K12: =COUNTIF(tx_CustName,$B12) -> 1 | L12: =MAXIFS(tx_Date,tx_CustID,$A12) -> 45635 | N12: 5 | O12: =INDEX($B$8:$B$57,MATCH($N12,$H$8:$H$57,0)) -> Paul Baker | P12: =INDEX($E$8:$E$57,MATCH($N12,$H$8:$H$57,0)) -> 8309.74 | Q12: =P12/$E$58 -> 0.036256601 | R12: =INDEX($C$8:$C$57,MATCH($N12,$H$8:$H$57,0)) -> 8 | S12: =INDEX($I$8:$I$57,MATCH($N12,$H$8:$H$57,0)) -> High-Value
A13: =Lists!G9 -> CUST006 | B13: =Lists!H9 -> Lisa Anderson | C13: =COUNTIF(tx_CustID,$A13) -> 5 | D13: =SUMIF(tx_CustID,$A13,tx_Qty) -> 20 | E13: =SUMIF(tx_CustID,$A13,tx_Total) -> 2039.8 | F13: =IF(C13=0,0,E13/C13) -> 407.96 | G13: =E13/$E$58 -> 0.0088999434 | H13: =RANK(E13,$E$8:$E$57,0)+COUNTIF($E$8:E13,E13)-1 -> 36 | I13: =IF(E13>=$E$3,"High-Value",IF(E13>=$E$4,"Mid-Value","Low-Value")) -> Low-Value | J13: =IF(C13>1,"Repeat","One-time") -> Repeat | K13: =COUNTIF(tx_CustName,$B13) -> 5 | L13: =MAXIFS(tx_Date,tx_CustID,$A13) -> 45676 | N13: 6 | O13: =INDEX($B$8:$B$57,MATCH($N13,$H$8:$H$57,0)) -> Dorothy Nelson | P13: =INDEX($E$8:$E$57,MATCH($N13,$H$8:$H$57,0)) -> 8269.79 | Q13: =P13/$E$58 -> 0.036082294 | R13: =INDEX($C$8:$C$57,MATCH($N13,$H$8:$H$57,0)) -> 6 | S13: =INDEX($I$8:$I$57,MATCH($N13,$H$8:$H$57,0)) -> High-Value
A14: =Lists!G10 -> CUST007 | B14: =Lists!H10 -> David Martinez | C14: =COUNTIF(tx_CustID,$A14) -> 6 | D14: =SUMIF(tx_CustID,$A14,tx_Qty) -> 16 | E14: =SUMIF(tx_CustID,$A14,tx_Total) -> 1809.84 | F14: =IF(C14=0,0,E14/C14) -> 301.64 | G14: =E14/$E$58 -> 0.0078965945 | H14: =RANK(E14,$E$8:$E$57,0)+COUNTIF($E$8:E14,E14)-1 -> 39 | I14: =IF(E14>=$E$3,"High-Value",IF(E14>=$E$4,"Mid-Value","Low-Value")) -> Low-Value | J14: =IF(C14>1,"Repeat","One-time") -> Repeat | K14: =COUNTIF(tx_CustName,$B14) -> 6 | L14: =MAXIFS(tx_Date,tx_CustID,$A14) -> 45648 | N14: 7 | O14: =INDEX($B$8:$B$57,MATCH($N14,$H$8:$H$57,0)) -> Karen Hill | P14: =INDEX($E$8:$E$57,MATCH($N14,$H$8:$H$57,0)) -> 8009.77 | Q14: =P14/$E$58 -> 0.034947789 | R14: =INDEX($C$8:$C$57,MATCH($N14,$H$8:$H$57,0)) -> 8 | S14: =INDEX($I$8:$I$57,MATCH($N14,$H$8:$H$57,0)) -> High-Value
A15: =Lists!G11 -> CUST008 | B15: =Lists!H11 -> Jennifer Taylor | C15: =COUNTIF(tx_CustID,$A15) -> 4 | D15: =SUMIF(tx_CustID,$A15,tx_Qty) -> 15 | E15: =SUMIF(tx_CustID,$A15,tx_Total) -> 4739.85 | F15: =IF(C15=0,0,E15/C15) -> 1184.9625 | G15: =E15/$E$58 -> 0.020680653 | H15: =RANK(E15,$E$8:$E$57,0)+COUNTIF($E$8:E15,E15)-1 -> 24 | I15: =IF(E15>=$E$3,"High-Value",IF(E15>=$E$4,"Mid-Value","Low-Value")) -> Mid-Value | J15: =IF(C15>1,"Repeat","One-time") -> Repeat | K15: =COUNTIF(tx_CustName,$B15) -> 4 | L15: =MAXIFS(tx_Date,tx_CustID,$A15) -> 45635 | N15: 8 | O15: =INDEX($B$8:$B$57,MATCH($N15,$H$8:$H$57,0)) -> Daniel King | P15: =INDEX($E$8:$E$57,MATCH($N15,$H$8:$H$57,0)) -> 7309.8 | Q15: =P15/$E$58 -> 0.031893718 | R15: =INDEX($C$8:$C$57,MATCH($N15,$H$8:$H$57,0)) -> 7 | S15: =INDEX($I$8:$I$57,MATCH($N15,$H$8:$H$57,0)) -> High-Value
A16: =Lists!G12 -> CUST009 | B16: =Lists!H12 -> Robert Thomas | C16: =COUNTIF(tx_CustID,$A16) -> 5 | D16: =SUMIF(tx_CustID,$A16,tx_Qty) -> 10 | E16: =SUMIF(tx_CustID,$A16,tx_Total) -> 3509.9 | F16: =IF(C16=0,0,E16/C16) -> 701.98 | G16: =E16/$E$58 -> 0.015314203 | H16: =RANK(E16,$E$8:$E$57,0)+COUNTIF($E$8:E16,E16)-1 -> 32 | I16: =IF(E16>=$E$3,"High-Value",IF(E16>=$E$4,"Mid-Value","Low-Value")) -> Low-Value | J16: =IF(C16>1,"Repeat","One-time") -> Repeat | K16: =COUNTIF(tx_CustName,$B16) -> 5 | L16: =MAXIFS(tx_Date,tx_CustID,$A16) -> 45756 | N16: 9 | O16: =INDEX($B$8:$B$57,MATCH($N16,$H$8:$H$57,0)) -> Lawrence Reed | P16: =INDEX($E$8:$E$57,MATCH($N16,$H$8:$H$57,0)) -> 6989.77 | Q16: =P16/$E$58 -> 0.030497381 | R16: =INDEX($C$8:$C$57,MATCH($N16,$H$8:$H$57,0)) -> 8 | S16: =INDEX($I$8:$I$57,MATCH($N16,$H$8:$H$57,0)) -> High-Value
A17: =Lists!G13 -> CUST010 | B17: =Lists!H13 -> Maria Garcia | C17: =COUNTIF(tx_CustID,$A17) -> 4 | D17: =SUMIF(tx_CustID,$A17,tx_Qty) -> 7 | E17: =SUMIF(tx_CustID,$A17,tx_Total) -> 1909.93 | F17: =IF(C17=0,0,E17/C17) -> 477.4825 | G17: =E17/$E$58 -> 0.0083333017 | H17: =RANK(E17,$E$8:$E$57,0)+COUNTIF($E$8:E17,E17)-1 -> 38 | I17: =IF(E17>=$E$3,"High-Value",IF(E17>=$E$4,"Mid-Value","Low-Value")) -> Low-Value | J17: =IF(C17>1,"Repeat","One-time") -> Repeat | K17: =COUNTIF(tx_CustName,$B17) -> 4 | L17: =MAXIFS(tx_Date,tx_CustID,$A17) -> 45604 | N17: 10 | O17: =INDEX($B$8:$B$57,MATCH($N17,$H$8:$H$57,0)) -> Joseph Jackson | P17: =INDEX($E$8:$E$57,MATCH($N17,$H$8:$H$57,0)) -> 6949.84 | Q17: =P17/$E$58 -> 0.03032316 | R17: =INDEX($C$8:$C$57,MATCH($N17,$H$8:$H$57,0)) -> 5 | S17: =INDEX($I$8:$I$57,MATCH($N17,$H$8:$H$57,0)) -> High-Value
A18: =Lists!G14 -> CUST011 | B18: =Lists!H14 -> William White | C18: =COUNTIF(tx_CustID,$A18) -> 3 | D18: =SUMIF(tx_CustID,$A18,tx_Qty) -> 9 | E18: =SUMIF(tx_CustID,$A18,tx_Total) -> 4749.91 | F18: =IF(C18=0,0,E18/C18) -> 1583.3033 | G18: =E18/$E$58 -> 0.020724546 | H18: =RANK(E18,$E$8:$E$57,0)+COUNTIF($E$8:E18,E18)-1 -> 23 | I18: =IF(E18>=$E$3,"High-Value",IF(E18>=$E$4,"Mid-Value","Low-Value")) -> Mid-Value | J18: =IF(C18>1,"Repeat","One-time") -> Repeat | K18: =COUNTIF(tx_CustName,$B18) -> 3 | L18: =MAXIFS(tx_Date,tx_CustID,$A18) -> 45686 | O18: Top 10 combined | P18: =SUM(P8:P17) -> 93867.66 | Q18: =SUM(Q8:Q17) -> 0.40955822
A19: =Lists!G15 -> CUST012 | B19: =Lists!H15 -> Patricia Moore | C19: =COUNTIF(tx_CustID,$A19) -> 8 | D19: =SUMIF(tx_CustID,$A19,tx_Qty) -> 27 | E19: =SUMIF(tx_CustID,$A19,tx_Total) -> 9799.73 | F19: =IF(C19=0,0,E19/C19) -> 1224.9662 | G19: =E19/$E$58 -> 0.042757644 | H19: =RANK(E19,$E$8:$E$57,0)+COUNTIF($E$8:E19,E19)-1 -> 4 | I19: =IF(E19>=$E$3,"High-Value",IF(E19>=$E$4,"Mid-Value","Low-Value")) -> High-Value | J19: =IF(C19>1,"Repeat","One-time") -> Repeat | K19: =COUNTIF(tx_CustName,$B19) -> 8 | L19: =MAXIFS(tx_Date,tx_CustID,$A19) -> 45607
A20: =Lists!G16 -> CUST013 | B20: =Lists!H16 -> Joseph Jackson | C20: =COUNTIF(tx_CustID,$A20) -> 5 | D20: =SUMIF(tx_CustID,$A20,tx_Qty) -> 16 | E20: =SUMIF(tx_CustID,$A20,tx_Total) -> 6949.84 | F20: =IF(C20=0,0,E20/C20) -> 1389.968 | G20: =E20/$E$58 -> 0.03032316 | H20: =RANK(E20,$E$8:$E$57,0)+COUNTIF($E$8:E20,E20)-1 -> 10 | I20: =IF(E20>=$E$3,"High-Value",IF(E20>=$E$4,"Mid-Value","Low-Value")) -> High-Value | J20: =IF(C20>1,"Repeat","One-time") -> Repeat | K20: =COUNTIF(tx_CustName,$B20) -> 5 | L20: =MAXIFS(tx_Date,tx_CustID,$A20) -> 45627
A21: =Lists!G17 -> CUST014 | B21: =Lists!H17 -> Linda Martin | C21: =COUNTIF(tx_CustID,$A21) -> 4 | D21: =SUMIF(tx_CustID,$A21,tx_Qty) -> 10 | E21: =SUMIF(tx_CustID,$A21,tx_Total) -> 1289.9 | F21: =IF(C21=0,0,E21/C21) -> 322.475 | G21: =E21/$E$58 -> 0.0056280209 | H21: =RANK(E21,$E$8:$E$57,0)+COUNTIF($E$8:E21,E21)-1 -> 43 | I21: =IF(E21>=$E$3,"High-Value",IF(E21>=$E$4,"Mid-Value","Low-Value")) -> Low-Value | J21: =IF(C21>1,"Repeat","One-time") -> Repeat | K21: =COUNTIF(tx_CustName,$B21) -> 4 | L21: =MAXIFS(tx_Date,tx_CustID,$A21) -> 45648 | N21: Repeat customers | Q21: =COUNTIF(J8:J57,"Repeat") -> 47
A22: =Lists!G18 -> CUST015 | B22: =Lists!H18 -> Richard Lee | C22: =COUNTIF(tx_CustID,$A22) -> 3 | D22: =SUMIF(tx_CustID,$A22,tx_Qty) -> 7 | E22: =SUMIF(tx_CustID,$A22,tx_Total) -> 739.93 | F22: =IF(C22=0,0,E22/C22) -> 246.64333 | G22: =E22/$E$58 -> 0.0032284219 | H22: =RANK(E22,$E$8:$E$57,0)+COUNTIF($E$8:E22,E22)-1 -> 46 | I22: =IF(E22>=$E$3,"High-Value",IF(E22>=$E$4,"Mid-Value","Low-Value")) -> Low-Value | J22: =IF(C22>1,"Repeat","One-time") -> Repeat | K22: =COUNTIF(tx_CustName,$B22) -> 3 | L22: =MAXIFS(tx_Date,tx_CustID,$A22) -> 45715 | N22: Average revenue per customer | Q22: =E58/COUNTIF(C8:C57,">0") -> 4583.8494
A23: =Lists!G19 -> CUST016 | B23: =Lists!H19 -> Elizabeth Hall | C23: =COUNTIF(tx_CustID,$A23) -> 4 | D23: =SUMIF(tx_CustID,$A23,tx_Qty) -> 14 | E23: =SUMIF(tx_CustID,$A23,tx_Total) -> 3649.86 | F23: =IF(C23=0,0,E23/C23) -> 912.465 | G23: =E23/$E$58 -> 0.015924869 | H23: =RANK(E23,$E$8:$E$57,0)+COUNTIF($E$8:E23,E23)-1 -> 31 | I23: =IF(E23>=$E$3,"High-Value",IF(E23>=$E$4,"Mid-Value","Low-Value")) -> Low-Value | J23: =IF(C23>1,"Repeat","One-time") -> Repeat | K23: =COUNTIF(tx_CustName,$B23) -> 4 | L23: =MAXIFS(tx_Date,tx_CustID,$A23) -> 45711
A24: =Lists!G20 -> CUST017 | B24: =Lists!H20 -> Charles Allen | C24: =COUNTIF(tx_CustID,$A24) -> 9 | D24: =SUMIF(tx_CustID,$A24,tx_Qty) -> 27 | E24: =SUMIF(tx_CustID,$A24,tx_Total) -> 5089.73 | F24: =IF(C24=0,0,E24/C24) -> 565.52556 | G24: =E24/$E$58 -> 0.02220723 | H24: =RANK(E24,$E$8:$E$57,0)+COUNTIF($E$8:E24,E24)-1 -> 20 | I24: =IF(E24>=$E$3,"High-Value",IF(E24>=$E$4,"Mid-Value","Low-Value")) -> Mid-Value | J24: =IF(C24>1,"Repeat","One-time") -> Repeat | K24: =COUNTIF(tx_CustName,$B24) -> 9 | L24: =MAXIFS(tx_Date,tx_CustID,$A24) -> 45724
A25: =Lists!G21 -> CUST018 | B25: =Lists!H21 -> Barbara Young | C25: =COUNTIF(tx_CustID,$A25) -> 5 | D25: =SUMIF(tx_CustID,$A25,tx_Qty) -> 20 | E25: =SUMIF(tx_CustID,$A25,tx_Total) -> 10649.8 | F25: =IF(C25=0,0,E25/C25) -> 2129.96 | G25: =E25/$E$58 -> 0.046466623 | H25: =RANK(E25,$E$8:$E$57,0)+COUNTIF($E$8:E25,E25)-1 -> 3 | I25: =IF(E25>=$E$3,"High-Value",IF(E25>=$E$4,"Mid-Value","Low-Value")) -> High-Value | J25: =IF(C25>1,"Repeat","One-time") -> Repeat | K25: =COUNTIF(tx_CustName,$B25) -> 5 | L25: =MAXIFS(tx_Date,tx_CustID,$A25) -> 45708
A26: =Lists!G22 -> CUST019 | B26: =Lists!H22 -> Daniel King | C26: =COUNTIF(tx_CustID,$A26) -> 7 | D26: =SUMIF(tx_CustID,$A26,tx_Qty) -> 20 | E26: =SUMIF(tx_CustID,$A26,tx_Total) -> 7309.8 | F26: =IF(C26=0,0,E26/C26) -> 1044.2571 | G26: =E26/$E$58 -> 0.031893718 | H26: =RANK(E26,$E$8:$E$57,0)+COUNTIF($E$8:E26,E26)-1 -> 8 | I26: =IF(E26>=$E$3,"High-Value",IF(E26>=$E$4,"Mid-Value","Low-Value")) -> High-Value | J26: =IF(C26>1,"Repeat","One-time") -> Repeat | K26: =COUNTIF(tx_CustName,$B26) -> 7 | L26: =MAXIFS(tx_Date,tx_CustID,$A26) -> 45660
A27: =Lists!G23 -> CUST020 | B27: =Lists!H23 -> Margaret Wright | C27: =COUNTIF(tx_CustID,$A27) -> 4 | D27: =SUMIF(tx_CustID,$A27,tx_Qty) -> 12 | E27: =SUMIF(tx_CustID,$A27,tx_Total) -> 2099.88 | F27: =IF(C27=0,0,E27/C27) -> 524.97 | G27: =E27/$E$58 -> 0.0091620811 | H27: =RANK(E27,$E$8:$E$57,0)+COUNTIF($E$8:E27,E27)-1 -> 35 | I27: =IF(E27>=$E$3,"High-Value",IF(E27>=$E$4,"Mid-Value","Low-Value")) -> Low-Value | J27: =IF(C27>1,"Repeat","One-time") -> Repeat | K27: =COUNTIF(tx_CustName,$B27) -> 4 | L27: =MAXIFS(tx_Date,tx_CustID,$A27) -> 45745
A28: =Lists!G24 -> CUST021 | B28: =Lists!H24 -> Kevin Scott | C28: =COUNTIF(tx_CustID,$A28) -> 6 | D28: =SUMIF(tx_CustID,$A28,tx_Qty) -> 13 | E28: =SUMIF(tx_CustID,$A28,tx_Total) -> 3259.87 | F28: =IF(C28=0,0,E28/C28) -> 543.31167 | G28: =E28/$E$58 -> 0.014223286 | H28: =RANK(E28,$E$8:$E$57,0)+COUNTIF($E$8:E28,E28)-1 -> 33 | I28: =IF(E28>=$E$3,"High-Value",IF(E28>=$E$4,"Mid-Value","Low-Value")) -> Low-Value | J28: =IF(C28>1,"Repeat","One-time") -> Repeat | K28: =COUNTIF(tx_CustName,$B28) -> 6 | L28: =MAXIFS(tx_Date,tx_CustID,$A28) -> 45704
A29: =Lists!G25 -> CUST022 | B29: =Lists!H25 -> Susan Green | C29: =COUNTIF(tx_CustID,$A29) -> 4 | D29: =SUMIF(tx_CustID,$A29,tx_Qty) -> 11 | E29: =SUMIF(tx_CustID,$A29,tx_Total) -> 1979.89 | F29: =IF(C29=0,0,E29/C29) -> 494.9725 | G29: =E29/$E$58 -> 0.0086385473 | H29: =RANK(E29,$E$8:$E$57,0)+COUNTIF($E$8:E29,E29)-1 -> 37 | I29: =IF(E29>=$E$3,"High-Value",IF(E29>=$E$4,"Mid-Value","Low-Value")) -> Low-Value | J29: =IF(C29>1,"Repeat","One-time") -> Repeat | K29: =COUNTIF(tx_CustName,$B29) -> 4 | L29: =MAXIFS(tx_Date,tx_CustID,$A29) -> 45682
A30: =Lists!G26 -> CUST023 | B30: =Lists!H26 -> Paul Baker | C30: =COUNTIF(tx_CustID,$A30) -> 8 | D30: =SUMIF(tx_CustID,$A30,tx_Qty) -> 26 | E30: =SUMIF(tx_CustID,$A30,tx_Total) -> 8309.74 | F30: =IF(C30=0,0,E30/C30) -> 1038.7175 | G30: =E30/$E$58 -> 0.036256601 | H30: =RANK(E30,$E$8:$E$57,0)+COUNTIF($E$8:E30,E30)-1 -> 5 | I30: =IF(E30>=$E$3,"High-Value",IF(E30>=$E$4,"Mid-Value","Low-Value")) -> High-Value | J30: =IF(C30>1,"Repeat","One-time") -> Repeat | K30: =COUNTIF(tx_CustName,$B30) -> 8 | L30: =MAXIFS(tx_Date,tx_CustID,$A30) -> 45739
A31: =Lists!G27 -> CUST024 | B31: =Lists!H27 -> Dorothy Nelson | C31: =COUNTIF(tx_CustID,$A31) -> 6 | D31: =SUMIF(tx_CustID,$A31,tx_Qty) -> 21 | E31: =SUMIF(tx_CustID,$A31,tx_Total) -> 8269.79 | F31: =IF(C31=0,0,E31/C31) -> 1378.2983 | G31: =E31/$E$58 -> 0.036082294 | H31: =RANK(E31,$E$8:$E$57,0)+COUNTIF($E$8:E31,E31)-1 -> 6 | I31: =IF(E31>=$E$3,"High-Value",IF(E31>=$E$4,"Mid-Value","Low-Value")) -> High-Value | J31: =IF(C31>1,"Repeat","One-time") -> Repeat | K31: =COUNTIF(tx_CustName,$B31) -> 6 | L31: =MAXIFS(tx_Date,tx_CustID,$A31) -> 45737
A32: =Lists!G28 -> CUST025 | B32: =Lists!H28 -> Mark Carter | C32: =COUNTIF(tx_CustID,$A32) -> 12 | D32: =SUMIF(tx_CustID,$A32,tx_Qty) -> 35 | E32: =SUMIF(tx_CustID,$A32,tx_Total) -> 15659.65 | F32: =IF(C32=0,0,E32/C32) -> 1304.9708 | G32: =E32/$E$58 -> 0.068325325 | H32: =RANK(E32,$E$8:$E$57,0)+COUNTIF($E$8:E32,E32)-1 -> 1 | I32: =IF(E32>=$E$3,"High-Value",IF(E32>=$E$4,"Mid-Value","Low-Value")) -> High-Value | J32: =IF(C32>1,"Repeat","One-time") -> Repeat | K32: =COUNTIF(tx_CustName,$B32) -> 12 | L32: =MAXIFS(tx_Date,tx_CustID,$A32) -> 45686
A33: =Lists!G29 -> CUST026 | B33: =Lists!H29 -> Karen Hill | C33: =COUNTIF(tx_CustID,$A33) -> 8 | D33: =SUMIF(tx_CustID,$A33,tx_Qty) -> 23 | E33: =SUMIF(tx_CustID,$A33,tx_Total) -> 8009.77 | F33: =IF(C33=0,0,E33/C33) -> 1001.2213 | G33: =E33/$E$58 -> 0.034947789 | H33: =RANK(E33,$E$8:$E$57,0)+COUNTIF($E$8:E33,E33)-1 -> 7 | I33: =IF(E33>=$E$3,"High-Value",IF(E33>=$E$4,"Mid-Value","Low-Value")) -> High-Value | J33: =IF(C33>1,"Repeat","One-time") -> Repeat | K33: =COUNTIF(tx_CustName,$B33) -> 8 | L33: =MAXIFS(tx_Date,tx_CustID,$A33) -> 45746
A34: =Lists!G30 -> CUST027 | B34: =Lists!H30 -> George Adams | C34: =COUNTIF(tx_CustID,$A34) -> 3 | D34: =SUMIF(tx_CustID,$A34,tx_Qty) -> 7 | E34: =SUMIF(tx_CustID,$A34,tx_Total) -> 3779.93 | F34: =IF(C34=0,0,E34/C34) -> 1259.9767 | G34: =E34/$E$58 -> 0.016492383 | H34: =RANK(E34,$E$8:$E$57,0)+COUNTIF($E$8:E34,E34)-1 -> 28 | I34: =IF(E34>=$E$3,"High-Value",IF(E34>=$E$4,"Mid-Value","Low-Value")) -> Low-Value | J34: =IF(C34>1,"Repeat","One-time") -> Repeat | K34: =COUNTIF(tx_CustName,$B34) -> 3 | L34: =MAXIFS(tx_Date,tx_CustID,$A34) -> 45608
... A57: =Lists!G53 -> CUST050 | B57: =Lists!H53 -> Julie Foster | C57: =COUNTIF(tx_CustID,$A57) -> 1 | D57: =SUMIF(tx_CustID,$A57,tx_Qty) -> 4 | E57: =SUMIF(tx_CustID,$A57,tx_Total) -> 239.96 | F57: =IF(C57=0,0,E57/C57) -> 239.96 | G57: =E57/$E$58 -> 0.0010469803 | H57: =RANK(E57,$E$8:$E$57,0)+COUNTIF($E$8:E57,E57)-1 -> 49 | I57: =IF(E57>=$E$3,"High-Value",IF(E57>=$E$4,"Mid-Value","Low-Value")) -> Low-Value | J57: =IF(C57>1,"Repeat","One-time") -> One-time | K57: =COUNTIF(tx_CustName,$B57) -> 1 | L57: =MAXIFS(tx_Date,tx_CustID,$A57) -> 45452
A58: Total | C58: =SUM(C8:C57) -> 250 | D58: =SUM(D8:D57) -> 753 | E58: =SUM(E8:E57) -> 229192.47 | F58: =E58/C58 -> 916.76988 | G58: =SUM(G8:G57) -> 1

Sheet Product_Analysis
M4: Most Sold Products
A5: Product_ID | B5: Product | C5: Category | D5: List Price | E5: Times Purchased | F5: Units Sold | G5: Revenue | H5: Revenue Share | I5: Rank as per Frequency | J5: Rank as per Units | K5: Rank as per Revenue | M5: Rank | N5: Product | O5: Units | P5: Revenue | Q5: Times Purchased
A6: =Lists!C4 -> P001 | B6: =Lists!D4 -> Laptop | C6: {=INDEX(tx_Category,MATCH($B6,tx_Product,0))} -> Electronics | D6: {=INDEX(tx_Price,MATCH($B6,tx_Product,0))} -> 899.99 | E6: =COUNTIF(tx_Product,$B6) -> 24 | F6: =SUMIF(tx_Product,$B6,tx_Qty) -> 75 | G6: =SUMIF(tx_Product,$B6,tx_Total) -> 67499.25 | H6: =G6/$G$16 -> 0.29450902 | I6: =RANK(E6,$E$6:$E$15,0)+COUNTIF($E$6:E6,E6)-1 -> 7 | J6: =RANK(F6,$F$6:$F$15,0)+COUNTIF($F$6:F6,F6)-1 -> 7 | K6: =RANK(G6,$G$6:$G$15,0)+COUNTIF($G$6:G6,G6)-1 -> 1 | M6: 1 | N6: =INDEX($B$6:$B$15,MATCH($M6,$J$6:$J$15,0)) -> Bookshelf | O6: =INDEX($F$6:$F$15,MATCH($M6,$J$6:$J$15,0)) -> 102 | P6: =INDEX($G$6:$G$15,MATCH($M6,$J$6:$J$15,0)) -> 15298.98 | Q6: =INDEX($E$6:$E$15,MATCH($M6,$J$6:$J$15,0)) -> 35
A7: =Lists!C5 -> P002 | B7: =Lists!D5 -> Smartphone | C7: {=INDEX(tx_Category,MATCH($B7,tx_Product,0))} -> Electronics | D7: {=INDEX(tx_Price,MATCH($B7,tx_Product,0))} -> 699.99 | E7: =COUNTIF(tx_Product,$B7) -> 31 | F7: =SUMIF(tx_Product,$B7,tx_Qty) -> 96 | G7: =SUMIF(tx_Product,$B7,tx_Total) -> 67199.04 | H7: =G7/$G$16 -> 0.29319916 | I7: =RANK(E7,$E$6:$E$15,0)+COUNTIF($E$6:E7,E7)-1 -> 3 | J7: =RANK(F7,$F$6:$F$15,0)+COUNTIF($F$6:F7,F7)-1 -> 2 | K7: =RANK(G7,$G$6:$G$15,0)+COUNTIF($G$6:G7,G7)-1 -> 2 | M7: 2 | N7: =INDEX($B$6:$B$15,MATCH($M7,$J$6:$J$15,0)) -> Smartphone | O7: =INDEX($F$6:$F$15,MATCH($M7,$J$6:$J$15,0)) -> 96 | P7: =INDEX($G$6:$G$15,MATCH($M7,$J$6:$J$15,0)) -> 67199.04 | Q7: =INDEX($E$6:$E$15,MATCH($M7,$J$6:$J$15,0)) -> 31
A8: =Lists!C6 -> P003 | B8: =Lists!D6 -> Headphones | C8: {=INDEX(tx_Category,MATCH($B8,tx_Product,0))} -> Electronics | D8: {=INDEX(tx_Price,MATCH($B8,tx_Product,0))} -> 149.99 | E8: =COUNTIF(tx_Product,$B8) -> 16 | F8: =SUMIF(tx_Product,$B8,tx_Qty) -> 47 | G8: =SUMIF(tx_Product,$B8,tx_Total) -> 7049.53 | H8: =G8/$G$16 -> 0.030758122 | I8: =RANK(E8,$E$6:$E$15,0)+COUNTIF($E$6:E8,E8)-1 -> 8 | J8: =RANK(F8,$F$6:$F$15,0)+COUNTIF($F$6:F8,F8)-1 -> 9 | K8: =RANK(G8,$G$6:$G$15,0)+COUNTIF($G$6:G8,G8)-1 -> 8 | M8: 3 | N8: =INDEX($B$6:$B$15,MATCH($M8,$J$6:$J$15,0)) -> Keyboard | O8: =INDEX($F$6:$F$15,MATCH($M8,$J$6:$J$15,0)) -> 89 | P8: =INDEX($G$6:$G$15,MATCH($M8,$J$6:$J$15,0)) -> 8009.11 | Q8: =INDEX($E$6:$E$15,MATCH($M8,$J$6:$J$15,0)) -> 34
A9: =Lists!C7 -> P004 | B9: =Lists!D7 -> Coffee Maker | C9: {=INDEX(tx_Category,MATCH($B9,tx_Product,0))} -> Appliances | D9: {=INDEX(tx_Price,MATCH($B9,tx_Product,0))} -> 79.99 | E9: =COUNTIF(tx_Product,$B9) -> 14 | F9: =SUMIF(tx_Product,$B9,tx_Qty) -> 39 | G9: =SUMIF(tx_Product,$B9,tx_Total) -> 3119.61 | H9: =G9/$G$16 -> 0.013611311 | I9: =RANK(E9,$E$6:$E$15,0)+COUNTIF($E$6:E9,E9)-1 -> 10 | J9: =RANK(F9,$F$6:$F$15,0)+COUNTIF($F$6:F9,F9)-1 -> 10 | K9: =RANK(G9,$G$6:$G$15,0)+COUNTIF($G$6:G9,G9)-1 -> 10 | M9: 4 | N9: =INDEX($B$6:$B$15,MATCH($M9,$J$6:$J$15,0)) -> Monitor | O9: =INDEX($F$6:$F$15,MATCH($M9,$J$6:$J$15,0)) -> 88 | P9: =INDEX($G$6:$G$15,MATCH($M9,$J$6:$J$15,0)) -> 21999.12 | Q9: =INDEX($E$6:$E$15,MATCH($M9,$J$6:$J$15,0)) -> 26
A10: =Lists!C8 -> P005 | B10: =Lists!D8 -> Blender | C10: {=INDEX(tx_Category,MATCH($B10,tx_Product,0))} -> Appliances | D10: {=INDEX(tx_Price,MATCH($B10,tx_Product,0))} -> 59.99 | E10: =COUNTIF(tx_Product,$B10) -> 29 | F10: =SUMIF(tx_Product,$B10,tx_Qty) -> 87 | G10: =SUMIF(tx_Product,$B10,tx_Total) -> 5219.13 | H10: =G10/$G$16 -> 0.022771821 | I10: =RANK(E10,$E$6:$E$15,0)+COUNTIF($E$6:E10,E10)-1 -> 4 | J10: =RANK(F10,$F$6:$F$15,0)+COUNTIF($F$6:F10,F10)-1 -> 5 | K10: =RANK(G10,$G$6:$G$15,0)+COUNTIF($G$6:G10,G10)-1 -> 9 | M10: 5 | N10: =INDEX($B$6:$B$15,MATCH($M10,$J$6:$J$15,0)) -> Blender | O10: =INDEX($F$6:$F$15,MATCH($M10,$J$6:$J$15,0)) -> 87 | P10: =INDEX($G$6:$G$15,MATCH($M10,$J$6:$J$15,0)) -> 5219.13 | Q10: =INDEX($E$6:$E$15,MATCH($M10,$J$6:$J$15,0)) -> 29
A11: =Lists!C9 -> P006 | B11: =Lists!D9 -> Office Chair | C11: {=INDEX(tx_Category,MATCH($B11,tx_Product,0))} -> Furniture | D11: {=INDEX(tx_Price,MATCH($B11,tx_Product,0))} -> 199.99 | E11: =COUNTIF(tx_Product,$B11) -> 15 | F11: =SUMIF(tx_Product,$B11,tx_Qty) -> 52 | G11: =SUMIF(tx_Product,$B11,tx_Total) -> 10399.48 | H11: =G11/$G$16 -> 0.04537444 | I11: =RANK(E11,$E$6:$E$15,0)+COUNTIF($E$6:E11,E11)-1 -> 9 | J11: =RANK(F11,$F$6:$F$15,0)+COUNTIF($F$6:F11,F11)-1 -> 8 | K11: =RANK(G11,$G$6:$G$15,0)+COUNTIF($G$6:G11,G11)-1 -> 6 | M11: 6 | N11: =INDEX($B$6:$B$15,MATCH($M11,$J$6:$J$15,0)) -> Desk | O11: =INDEX($F$6:$F$15,MATCH($M11,$J$6:$J$15,0)) -> 78 | P11: =INDEX($G$6:$G$15,MATCH($M11,$J$6:$J$15,0)) -> 23399.22 | Q11: =INDEX($E$6:$E$15,MATCH($M11,$J$6:$J$15,0)) -> 26
A12: =Lists!C10 -> P007 | B12: =Lists!D10 -> Desk | C12: {=INDEX(tx_Category,MATCH($B12,tx_Product,0))} -> Furniture | D12: {=INDEX(tx_Price,MATCH($B12,tx_Product,0))} -> 299.99 | E12: =COUNTIF(tx_Product,$B12) -> 26 | F12: =SUMIF(tx_Product,$B12,tx_Qty) -> 78 | G12: =SUMIF(tx_Product,$B12,tx_Total) -> 23399.22 | H12: =G12/$G$16 -> 0.10209419 | I12: =RANK(E12,$E$6:$E$15,0)+COUNTIF($E$6:E12,E12)-1 -> 5 | J12: =RANK(F12,$F$6:$F$15,0)+COUNTIF($F$6:F12,F12)-1 -> 6 | K12: =RANK(G12,$G$6:$G$15,0)+COUNTIF($G$6:G12,G12)-1 -> 3 | M12: 7 | N12: =INDEX($B$6:$B$15,MATCH($M12,$J$6:$J$15,0)) -> Laptop | O12: =INDEX($F$6:$F$15,MATCH($M12,$J$6:$J$15,0)) -> 75 | P12: =INDEX($G$6:$G$15,MATCH($M12,$J$6:$J$15,0)) -> 67499.25 | Q12: =INDEX($E$6:$E$15,MATCH($M12,$J$6:$J$15,0)) -> 24
A13: =Lists!C11 -> P008 | B13: =Lists!D11 -> Bookshelf | C13: {=INDEX(tx_Category,MATCH($B13,tx_Product,0))} -> Furniture | D13: {=INDEX(tx_Price,MATCH($B13,tx_Product,0))} -> 149.99 | E13: =COUNTIF(tx_Product,$B13) -> 35 | F13: =SUMIF(tx_Product,$B13,tx_Qty) -> 102 | G13: =SUMIF(tx_Product,$B13,tx_Total) -> 15298.98 | H13: =G13/$G$16 -> 0.066751669 | I13: =RANK(E13,$E$6:$E$15,0)+COUNTIF($E$6:E13,E13)-1 -> 1 | J13: =RANK(F13,$F$6:$F$15,0)+COUNTIF($F$6:F13,F13)-1 -> 1 | K13: =RANK(G13,$G$6:$G$15,0)+COUNTIF($G$6:G13,G13)-1 -> 5 | M13: 8 | N13: =INDEX($B$6:$B$15,MATCH($M13,$J$6:$J$15,0)) -> Office Chair | O13: =INDEX($F$6:$F$15,MATCH($M13,$J$6:$J$15,0)) -> 52 | P13: =INDEX($G$6:$G$15,MATCH($M13,$J$6:$J$15,0)) -> 10399.48 | Q13: =INDEX($E$6:$E$15,MATCH($M13,$J$6:$J$15,0)) -> 15
A14: =Lists!C12 -> P009 | B14: =Lists!D12 -> Monitor | C14: {=INDEX(tx_Category,MATCH($B14,tx_Product,0))} -> Electronics | D14: {=INDEX(tx_Price,MATCH($B14,tx_Product,0))} -> 249.99 | E14: =COUNTIF(tx_Product,$B14) -> 26 | F14: =SUMIF(tx_Product,$B14,tx_Qty) -> 88 | G14: =SUMIF(tx_Product,$B14,tx_Total) -> 21999.12 | H14: =G14/$G$16 -> 0.095985352 | I14: =RANK(E14,$E$6:$E$15,0)+COUNTIF($E$6:E14,E14)-1 -> 6 | J14: =RANK(F14,$F$6:$F$15,0)+COUNTIF($F$6:F14,F14)-1 -> 4 | K14: =RANK(G14,$G$6:$G$15,0)+COUNTIF($G$6:G14,G14)-1 -> 4 | M14: 9 | N14: =INDEX($B$6:$B$15,MATCH($M14,$J$6:$J$15,0)) -> Headphones | O14: =INDEX($F$6:$F$15,MATCH($M14,$J$6:$J$15,0)) -> 47 | P14: =INDEX($G$6:$G$15,MATCH($M14,$J$6:$J$15,0)) -> 7049.53 | Q14: =INDEX($E$6:$E$15,MATCH($M14,$J$6:$J$15,0)) -> 16
A15: =Lists!C13 -> P010 | B15: =Lists!D13 -> Keyboard | C15: {=INDEX(tx_Category,MATCH($B15,tx_Product,0))} -> Electronics | D15: {=INDEX(tx_Price,MATCH($B15,tx_Product,0))} -> 89.99 | E15: =COUNTIF(tx_Product,$B15) -> 34 | F15: =SUMIF(tx_Product,$B15,tx_Qty) -> 89 | G15: =SUMIF(tx_Product,$B15,tx_Total) -> 8009.11 | H15: =G15/$G$16 -> 0.034944909 | I15: =RANK(E15,$E$6:$E$15,0)+COUNTIF($E$6:E15,E15)-1 -> 2 | J15: =RANK(F15,$F$6:$F$15,0)+COUNTIF($F$6:F15,F15)-1 -> 3 | K15: =RANK(G15,$G$6:$G$15,0)+COUNTIF($G$6:G15,G15)-1 -> 7 | M15: 10 | N15: =INDEX($B$6:$B$15,MATCH($M15,$J$6:$J$15,0)) -> Coffee Maker | O15: =INDEX($F$6:$F$15,MATCH($M15,$J$6:$J$15,0)) -> 39 | P15: =INDEX($G$6:$G$15,MATCH($M15,$J$6:$J$15,0)) -> 3119.61 | Q15: =INDEX($E$6:$E$15,MATCH($M15,$J$6:$J$15,0)) -> 14
A16: Total | E16: =SUM(E6:E15) -> 250 | F16: =SUM(F6:F15) -> 753 | G16: =SUM(G6:G15) -> 229192.47 | H16: =SUM(H6:H15) -> 1
A19: Most frequently purchased | B19: {=INDEX($B$6:$B$15,MATCH(1,$I$6:$I$15,0))} -> Bookshelf | C19: =MAX($E$6:$E$15) -> 35
A20: Most units sold | B20: {=INDEX($B$6:$B$15,MATCH(1,$J$6:$J$15,0))} -> Bookshelf | C20: =MAX($F$6:$F$15) -> 102
A21: Highest revenue product | B21: {=INDEX($B$6:$B$15,MATCH(1,$K$6:$K$15,0))} -> Laptop | C21: =MAX($G$6:$G$15) -> 67499.25
A22: Least frequently purchased product | B22: {=INDEX($B$6:$B$15,MATCH(10,$I$6:$I$15,0))} -> Coffee Maker | C22: =MIN($E$6:$E$15) -> 14

Sheet Pivot_Summaries
A3: Revenue by Region and Category | J3: Monthly trend
A4: Region | B4: =Lists!B4 -> Appliances | C4: =Lists!B5 -> Electronics | D4: =Lists!B6 -> Furniture | E4: Total | J4: Month Start | K4: Month End | L4: Revenue | M4: Transactions | N4: Units | O4: MoM | P4: Coverage | Q4: Label
A5: =Lists!A4 -> Central | B5: =SUMIFS(tx_Total,tx_Region,$A5,tx_Category,B$4) -> 1999.71 | C5: =SUMIFS(tx_Total,tx_Region,$A5,tx_Category,C$4) -> 24889.33 | D5: =SUMIFS(tx_Total,tx_Region,$A5,tx_Category,D$4) -> 14399.3 | E5: =SUM(B5:D5) -> 41288.34 | J5: =DATE(YEAR(MIN(tx_Date)),MONTH(MIN(tx_Date)),1) -> 45383 | K5: =EOMONTH(J5,0) -> 45412 | L5: =SUMIFS(tx_Total,tx_Date,">="&J5,tx_Date,"<="&K5) -> 20919.33 | M5: =COUNTIFS(tx_Date,">="&J5,tx_Date,"<="&K5) -> 21 | N5: =SUMIFS(tx_Qty,tx_Date,">="&J5,tx_Date,"<="&K5) -> 67 | P5: =IF(AND(MIN(tx_Date)<=J5,MAX(tx_Date)>=K5),"Full","Partial") -> Partial | Q5: =TEXT(J5,"mmm-yy") -> Apr-24
A6: =Lists!A5 -> East | B6: =SUMIFS(tx_Total,tx_Region,$A6,tx_Category,B$4) -> 2239.67 | C6: =SUMIFS(tx_Total,tx_Region,$A6,tx_Category,C$4) -> 50649.01 | D6: =SUMIFS(tx_Total,tx_Region,$A6,tx_Category,D$4) -> 6399.71 | E6: =SUM(B6:D6) -> 59288.39 | J6: =EDATE(J5,1) -> 45413 | K6: =EOMONTH(J6,0) -> 45443 | L6: =SUMIFS(tx_Total,tx_Date,">="&J6,tx_Date,"<="&K6) -> 17039.35 | M6: =COUNTIFS(tx_Date,">="&J6,tx_Date,"<="&K6) -> 19 | N6: =SUMIFS(tx_Qty,tx_Date,">="&J6,tx_Date,"<="&K6) -> 65 | O6: =IF(L5=0,"",L6/L5-1) -> -0.18547344 | P6: =IF(AND(MIN(tx_Date)<=J6,MAX(tx_Date)>=K6),"Full","Partial") -> Full | Q6: =TEXT(J6,"mmm-yy") -> May-24
A7: =Lists!A6 -> North | B7: =SUMIFS(tx_Total,tx_Region,$A7,tx_Category,B$4) -> 1119.84 | C7: =SUMIFS(tx_Total,tx_Region,$A7,tx_Category,C$4) -> 39239.04 | D7: =SUMIFS(tx_Total,tx_Region,$A7,tx_Category,D$4) -> 10449.43 | E7: =SUM(B7:D7) -> 50808.31 | J7: =EDATE(J6,1) -> 45444 | K7: =EOMONTH(J7,0) -> 45473 | L7: =SUMIFS(tx_Total,tx_Date,">="&J7,tx_Date,"<="&K7) -> 19299.45 | M7: =COUNTIFS(tx_Date,">="&J7,tx_Date,"<="&K7) -> 19 | N7: =SUMIFS(tx_Qty,tx_Date,">="&J7,tx_Date,"<="&K7) -> 55 | O7: =IF(L6=0,"",L7/L6-1) -> 0.13264004 | P7: =IF(AND(MIN(tx_Date)<=J7,MAX(tx_Date)>=K7),"Full","Partial") -> Full | Q7: =TEXT(J7,"mmm-yy") -> Jun-24
A8: =Lists!A7 -> South | B8: =SUMIFS(tx_Total,tx_Region,$A8,tx_Category,B$4) -> 1099.83 | C8: =SUMIFS(tx_Total,tx_Region,$A8,tx_Category,C$4) -> 25549.32 | D8: =SUMIFS(tx_Total,tx_Region,$A8,tx_Category,D$4) -> 9749.6 | E8: =SUM(B8:D8) -> 36398.75 | J8: =EDATE(J7,1) -> 45474 | K8: =EOMONTH(J8,0) -> 45504 | L8: =SUMIFS(tx_Total,tx_Date,">="&J8,tx_Date,"<="&K8) -> 18479.4 | M8: =COUNTIFS(tx_Date,">="&J8,tx_Date,"<="&K8) -> 24 | N8: =SUMIFS(tx_Qty,tx_Date,">="&J8,tx_Date,"<="&K8) -> 60 | O8: =IF(L7=0,"",L8/L7-1) -> -0.042490848 | P8: =IF(AND(MIN(tx_Date)<=J8,MAX(tx_Date)>=K8),"Full","Partial") -> Full | Q8: =TEXT(J8,"mmm-yy") -> Jul-24
A9: =Lists!A8 -> West | B9: =SUMIFS(tx_Total,tx_Region,$A9,tx_Category,B$4) -> 1879.69 | C9: =SUMIFS(tx_Total,tx_Region,$A9,tx_Category,C$4) -> 31429.35 | D9: =SUMIFS(tx_Total,tx_Region,$A9,tx_Category,D$4) -> 8099.64 | E9: =SUM(B9:D9) -> 41408.68 | J9: =EDATE(J8,1) -> 45505 | K9: =EOMONTH(J9,0) -> 45535 | L9: =SUMIFS(tx_Total,tx_Date,">="&J9,tx_Date,"<="&K9) -> 15759.43 | M9: =COUNTIFS(tx_Date,">="&J9,tx_Date,"<="&K9) -> 18 | N9: =SUMIFS(tx_Qty,tx_Date,">="&J9,tx_Date,"<="&K9) -> 57 | O9: =IF(L8=0,"",L9/L8-1) -> -0.1471893 | P9: =IF(AND(MIN(tx_Date)<=J9,MAX(tx_Date)>=K9),"Full","Partial") -> Full | Q9: =TEXT(J9,"mmm-yy") -> Aug-24
A10: Total | B10: =SUM(B5:B9) -> 8338.74 | C10: =SUM(C5:C9) -> 171756.05 | D10: =SUM(D5:D9) -> 49097.68 | E10: =SUM(E5:E9) -> 229192.47 | J10: =EDATE(J9,1) -> 45536 | K10: =EOMONTH(J10,0) -> 45565 | L10: =SUMIFS(tx_Total,tx_Date,">="&J10,tx_Date,"<="&K10) -> 12989.51 | M10: =COUNTIFS(tx_Date,">="&J10,tx_Date,"<="&K10) -> 19 | N10: =SUMIFS(tx_Qty,tx_Date,">="&J10,tx_Date,"<="&K10) -> 49 | O10: =IF(L9=0,"",L10/L9-1) -> -0.1757627 | P10: =IF(AND(MIN(tx_Date)<=J10,MAX(tx_Date)>=K10),"Full","Partial") -> Full | Q10: =TEXT(J10,"mmm-yy") -> Sep-24
J11: =EDATE(J10,1) -> 45566 | K11: =EOMONTH(J11,0) -> 45596 | L11: =SUMIFS(tx_Total,tx_Date,">="&J11,tx_Date,"<="&K11) -> 20609.52 | M11: =COUNTIFS(tx_Date,">="&J11,tx_Date,"<="&K11) -> 16 | N11: =SUMIFS(tx_Qty,tx_Date,">="&J11,tx_Date,"<="&K11) -> 48 | O11: =IF(L10=0,"",L11/L10-1) -> 0.58662798 | P11: =IF(AND(MIN(tx_Date)<=J11,MAX(tx_Date)>=K11),"Full","Partial") -> Full | Q11: =TEXT(J11,"mmm-yy") -> Oct-24
J12: =EDATE(J11,1) -> 45597 | K12: =EOMONTH(J12,0) -> 45626 | L12: =SUMIFS(tx_Total,tx_Date,">="&J12,tx_Date,"<="&K12) -> 12309.44 | M12: =COUNTIFS(tx_Date,">="&J12,tx_Date,"<="&K12) -> 17 | N12: =SUMIFS(tx_Qty,tx_Date,">="&J12,tx_Date,"<="&K12) -> 56 | O12: =IF(L11=0,"",L12/L11-1) -> -0.40273039 | P12: =IF(AND(MIN(tx_Date)<=J12,MAX(tx_Date)>=K12),"Full","Partial") -> Full | Q12: =TEXT(J12,"mmm-yy") -> Nov-24
A13: Region summary | J13: =EDATE(J12,1) -> 45627 | K13: =EOMONTH(J13,0) -> 45657 | L13: =SUMIFS(tx_Total,tx_Date,">="&J13,tx_Date,"<="&K13) -> 23039.3 | M13: =COUNTIFS(tx_Date,">="&J13,tx_Date,"<="&K13) -> 25 | N13: =SUMIFS(tx_Qty,tx_Date,">="&J13,tx_Date,"<="&K13) -> 70 | O13: =IF(L12=0,"",L13/L12-1) -> 0.87167735 | P13: =IF(AND(MIN(tx_Date)<=J13,MAX(tx_Date)>=K13),"Full","Partial") -> Full | Q13: =TEXT(J13,"mmm-yy") -> Dec-24
A14: Region | B14: Revenue | C14: Transactions | D14: Units | E14: Avg Order Value | F14: Share of Revenue | G14: Rank | J14: =EDATE(J13,1) -> 45658 | K14: =EOMONTH(J14,0) -> 45688 | L14: =SUMIFS(tx_Total,tx_Date,">="&J14,tx_Date,"<="&K14) -> 25799.15 | M14: =COUNTIFS(tx_Date,">="&J14,tx_Date,"<="&K14) -> 26 | N14: =SUMIFS(tx_Qty,tx_Date,">="&J14,tx_Date,"<="&K14) -> 85 | O14: =IF(L13=0,"",L14/L13-1) -> 0.1197888 | P14: =IF(AND(MIN(tx_Date)<=J14,MAX(tx_Date)>=K14),"Full","Partial") -> Full | Q14: =TEXT(J14,"mmm-yy") -> Jan-25
A15: =Lists!A4 -> Central | B15: =SUMIFS(tx_Total,tx_Region,$A15) -> 41288.34 | C15: =COUNTIFS(tx_Region,$A15) -> 54 | D15: =SUMIFS(tx_Qty,tx_Region,$A15) -> 166 | E15: =IF(C15=0,0,B15/C15) -> 764.59889 | F15: =B15/$B$20 -> 0.18014702 | G15: =RANK(B15,$B$15:$B$19,0)+COUNTIF($B$15:B15,B15)-1 -> 4 | J15: =EDATE(J14,1) -> 45689 | K15: =EOMONTH(J15,0) -> 45716 | L15: =SUMIFS(tx_Total,tx_Date,">="&J15,tx_Date,"<="&K15) -> 16069.38 | M15: =COUNTIFS(tx_Date,">="&J15,tx_Date,"<="&K15) -> 20 | N15: =SUMIFS(tx_Qty,tx_Date,">="&J15,tx_Date,"<="&K15) -> 62 | O15: =IF(L14=0,"",L15/L14-1) -> -0.37713529 | P15: =IF(AND(MIN(tx_Date)<=J15,MAX(tx_Date)>=K15),"Full","Partial") -> Full | Q15: =TEXT(J15,"mmm-yy") -> Feb-25
A16: =Lists!A5 -> East | B16: =SUMIFS(tx_Total,tx_Region,$A16) -> 59288.39 | C16: =COUNTIFS(tx_Region,$A16) -> 48 | D16: =SUMIFS(tx_Qty,tx_Region,$A16) -> 161 | E16: =IF(C16=0,0,B16/C16) -> 1235.1748 | F16: =B16/$B$20 -> 0.25868385 | G16: =RANK(B16,$B$15:$B$19,0)+COUNTIF($B$15:B16,B16)-1 -> 1 | J16: =EDATE(J15,1) -> 45717 | K16: =EOMONTH(J16,0) -> 45747 | L16: =SUMIFS(tx_Total,tx_Date,">="&J16,tx_Date,"<="&K16) -> 19899.38 | M16: =COUNTIFS(tx_Date,">="&J16,tx_Date,"<="&K16) -> 19 | N16: =SUMIFS(tx_Qty,tx_Date,">="&J16,tx_Date,"<="&K16) -> 62 | O16: =IF(L15=0,"",L16/L15-1) -> 0.23834149 | P16: =IF(AND(MIN(tx_Date)<=J16,MAX(tx_Date)>=K16),"Full","Partial") -> Full | Q16: =TEXT(J16,"mmm-yy") -> Mar-25
A17: =Lists!A6 -> North | B17: =SUMIFS(tx_Total,tx_Region,$A17) -> 50808.31 | C17: =COUNTIFS(tx_Region,$A17) -> 59 | D17: =SUMIFS(tx_Qty,tx_Region,$A17) -> 169 | E17: =IF(C17=0,0,B17/C17) -> 861.1578 | F17: =B17/$B$20 -> 0.22168403 | G17: =RANK(B17,$B$15:$B$19,0)+COUNTIF($B$15:B17,B17)-1 -> 2 | J17: =EDATE(J16,1) -> 45748 | K17: =EOMONTH(J17,0) -> 45777 | L17: =SUMIFS(tx_Total,tx_Date,">="&J17,tx_Date,"<="&K17) -> 6979.83 | M17: =COUNTIFS(tx_Date,">="&J17,tx_Date,"<="&K17) -> 7 | N17: =SUMIFS(tx_Qty,tx_Date,">="&J17,tx_Date,"<="&K17) -> 17 | O17: =IF(L16=0,"",L17/L16-1) -> -0.64924385 | P17: =IF(AND(MIN(tx_Date)<=J17,MAX(tx_Date)>=K17),"Full","Partial") -> Partial | Q17: =TEXT(J17,"mmm-yy") -> Apr-25
A18: =Lists!A7 -> South | B18: =SUMIFS(tx_Total,tx_Region,$A18) -> 36398.75 | C18: =COUNTIFS(tx_Region,$A18) -> 42 | D18: =SUMIFS(tx_Qty,tx_Region,$A18) -> 125 | E18: =IF(C18=0,0,B18/C18) -> 866.6369 | F18: =B18/$B$20 -> 0.15881303 | G18: =RANK(B18,$B$15:$B$19,0)+COUNTIF($B$15:B18,B18)-1 -> 5 | J18: Total | L18: =SUM(L5:L17) -> 229192.47 | M18: =SUM(M5:M17) -> 250 | N18: =SUM(N5:N17) -> 753
A19: =Lists!A8 -> West | B19: =SUMIFS(tx_Total,tx_Region,$A19) -> 41408.68 | C19: =COUNTIFS(tx_Region,$A19) -> 47 | D19: =SUMIFS(tx_Qty,tx_Region,$A19) -> 132 | E19: =IF(C19=0,0,B19/C19) -> 881.03574 | F19: =B19/$B$20 -> 0.18067208 | G19: =RANK(B19,$B$15:$B$19,0)+COUNTIF($B$15:B19,B19)-1 -> 3
A20: Total | B20: =SUM(B15:B19) -> 229192.47 | C20: =SUM(C15:C19) -> 250 | D20: =SUM(D15:D19) -> 753 | E20: =B20/C20 -> 916.76988 | F20: =SUM(F15:F19) -> 1
A23: Category summary
A24: Category | B24: Revenue | C24: Transactions | D24: Units | E24: Avg Order Value | F24: Share of Revenue
A25: =Lists!B4 -> Appliances | B25: =SUMIFS(tx_Total,tx_Category,$A25) -> 8338.74 | C25: =COUNTIFS(tx_Category,$A25) -> 43 | D25: =SUMIFS(tx_Qty,tx_Category,$A25) -> 126 | E25: =IF(C25=0,0,B25/C25) -> 193.92419 | F25: =B25/B$28 -> 0.036383132
A26: =Lists!B5 -> Electronics | B26: =SUMIFS(tx_Total,tx_Category,$A26) -> 171756.05 | C26: =COUNTIFS(tx_Category,$A26) -> 131 | D26: =SUMIFS(tx_Qty,tx_Category,$A26) -> 395 | E26: =IF(C26=0,0,B26/C26) -> 1311.1149 | F26: =B26/B$28 -> 0.74939657
A27: =Lists!B6 -> Furniture | B27: =SUMIFS(tx_Total,tx_Category,$A27) -> 49097.68 | C27: =COUNTIFS(tx_Category,$A27) -> 76 | D27: =SUMIFS(tx_Qty,tx_Category,$A27) -> 232 | E27: =IF(C27=0,0,B27/C27) -> 646.02211 | F27: =B27/B$28 -> 0.2142203
A28: Total | B28: =SUM(B25:B27) -> 229192.47 | C28: =SUM(C25:C27) -> 250 | D28: =SUM(D25:D27) -> 753 | E28: =B28/C28 -> 916.76988 | F28: =SUM(F25:F27) -> 1
A31: Payment method summary
A32: Payment_Method | B32: Revenue | C32: Transactions | D32: Units | E32: Avg Order Value | F32: Share of Revenue
A33: =Lists!E4 -> Cash | B33: =SUMIFS(tx_Total,tx_Pay,$A33) -> 57427.79 | C33: =COUNTIFS(tx_Pay,$A33) -> 76 | D33: =SUMIFS(tx_Qty,tx_Pay,$A33) -> 221 | E33: =IF(C33=0,0,B33/C33) -> 755.62882 | F33: =B33/B$37 -> 0.25056578
A34: =Lists!E5 -> Credit Card | B34: =SUMIFS(tx_Total,tx_Pay,$A34) -> 61447.96 | C34: =COUNTIFS(tx_Pay,$A34) -> 68 | D34: =SUMIFS(tx_Qty,tx_Pay,$A34) -> 204 | E34: =IF(C34=0,0,B34/C34) -> 903.64647 | F34: =B34/B$37 -> 0.26810636
A35: =Lists!E6 -> Debit Card | B35: =SUMIFS(tx_Total,tx_Pay,$A35) -> 52118.31 | C35: =COUNTIFS(tx_Pay,$A35) -> 54 | D35: =SUMIFS(tx_Qty,tx_Pay,$A35) -> 169 | E35: =IF(C35=0,0,B35/C35) -> 965.15389 | F35: =B35/B$37 -> 0.22739975
A36: =Lists!E7 -> PayPal | B36: =SUMIFS(tx_Total,tx_Pay,$A36) -> 58198.41 | C36: =COUNTIFS(tx_Pay,$A36) -> 52 | D36: =SUMIFS(tx_Qty,tx_Pay,$A36) -> 159 | E36: =IF(C36=0,0,B36/C36) -> 1119.2002 | F36: =B36/B$37 -> 0.25392811
A37: Total | B37: =SUM(B33:B36) -> 229192.47 | C37: =SUM(C33:C36) -> 250 | D37: =SUM(D33:D36) -> 753 | E37: =B37/C37 -> 916.76988 | F37: =SUM(F33:F36) -> 1
A40: Customer segment summary
A41: Customer_Segment | B41: Revenue | C41: Transactions | D41: Units | E41: Avg Order Value | F41: Share of Revenue
A42: =Lists!F4 -> Basic | B42: =SUMIFS(tx_Total,tx_Segment,$A42) -> 62177.81 | C42: =COUNTIFS(tx_Segment,$A42) -> 74 | D42: =SUMIFS(tx_Qty,tx_Segment,$A42) -> 219 | E42: =IF(C42=0,0,B42/C42) -> 840.24068 | F42: =B42/B$45 -> 0.27129081
A43: =Lists!F5 -> Premium | B43: =SUMIFS(tx_Total,tx_Segment,$A43) -> 84657.12 | C43: =COUNTIFS(tx_Segment,$A43) -> 95 | D43: =SUMIFS(tx_Qty,tx_Segment,$A43) -> 288 | E43: =IF(C43=0,0,B43/C43) -> 891.12758 | F43: =B43/B$45 -> 0.3693713
A44: =Lists!F6 -> Standard | B44: =SUMIFS(tx_Total,tx_Segment,$A44) -> 82357.54 | C44: =COUNTIFS(tx_Segment,$A44) -> 81 | D44: =SUMIFS(tx_Qty,tx_Segment,$A44) -> 246 | E44: =IF(C44=0,0,B44/C44) -> 1016.7598 | F44: =B44/B$45 -> 0.3593379
A45: Total | B45: =SUM(B42:B44) -> 229192.47 | C45: =SUM(C42:C44) -> 250 | D45: =SUM(D42:D44) -> 753 | E45: =B45/C45 -> 916.76988 | F45: =SUM(F42:F44) -> 1

Sheet Filter_Tool
A3: Region | B3: East
A4: Category | B4: Electronics
A5: Min Total_Amount | B5: 2000
A6: Matching transactions | B6: =MAX($N$10:$N$259) -> 11
A7: Revenue of matches | B7: =SUMPRODUCT($M$10:$M$259,tx_Total) -> 38899.53
A9: Sr. no | B9: Transaction_ID | C9: Date | D9: Customer_Name | E9: Product_Name | F9: Category | G9: Region | H9: Quantity | I9: Total_Amount | J9: Source row | L9: Helper: idx | M9: Helper: match | N9: Helper: running
A10: =IF(ROWS($A$10:A10)<=$B$6,ROWS($A$10:A10),"") -> 1 | B10: {=IF($J10="","",INDEX(tx_ID,$J10))} -> TRX0135 | C10: {=IF($J10="","",INDEX(tx_Date,$J10))} -> 45405 | D10: {=IF($J10="","",INDEX(tx_CustName,$J10))} -> Robert Thomas | E10: {=IF($J10="","",INDEX(tx_Product,$J10))} -> Laptop | F10: {=IF($J10="","",INDEX(tx_Category,$J10))} -> Electronics | G10: {=IF($J10="","",INDEX(tx_Region,$J10))} -> East | H10: {=IF($J10="","",INDEX(tx_Qty,$J10))} -> 3 | I10: {=IF($J10="","",INDEX(tx_Total,$J10))} -> 2699.97 | J10: =IF($A10="","",MATCH($A10,$N$10:$N$259,0)) -> 9 | L10: =ROW()-ROW($L$9) -> 1 | M10: {=IF(AND(OR($B$3="All",INDEX(tx_Region,L10)=$B$3),OR($B$4="All",INDEX(tx_Category,L10)=$B$4),INDEX(tx_Total,L10)>=$B$5),1,0)} -> 0 | N10: =M10 -> 0
A11: =IF(ROWS($A$10:A11)<=$B$6,ROWS($A$10:A11),"") -> 2 | B11: {=IF($J11="","",INDEX(tx_ID,$J11))} -> TRX0239 | C11: {=IF($J11="","",INDEX(tx_Date,$J11))} -> 45413 | D11: {=IF($J11="","",INDEX(tx_CustName,$J11))} -> Patricia Moore | E11: {=IF($J11="","",INDEX(tx_Product,$J11))} -> Smartphone | F11: {=IF($J11="","",INDEX(tx_Category,$J11))} -> Electronics | G11: {=IF($J11="","",INDEX(tx_Region,$J11))} -> East | H11: {=IF($J11="","",INDEX(tx_Qty,$J11))} -> 4 | I11: {=IF($J11="","",INDEX(tx_Total,$J11))} -> 2799.96 | J11: =IF($A11="","",MATCH($A11,$N$10:$N$259,0)) -> 22 | L11: =ROW()-ROW($L$9) -> 2 | M11: {=IF(AND(OR($B$3="All",INDEX(tx_Region,L11)=$B$3),OR($B$4="All",INDEX(tx_Category,L11)=$B$4),INDEX(tx_Total,L11)>=$B$5),1,0)} -> 0 | N11: =N10+M11 -> 0
A12: =IF(ROWS($A$10:A12)<=$B$6,ROWS($A$10:A12),"") -> 3 | B12: {=IF($J12="","",INDEX(tx_ID,$J12))} -> TRX0044 | C12: {=IF($J12="","",INDEX(tx_Date,$J12))} -> 45459 | D12: {=IF($J12="","",INDEX(tx_CustName,$J12))} -> Edward Mitchell | E12: {=IF($J12="","",INDEX(tx_Product,$J12))} -> Laptop | F12: {=IF($J12="","",INDEX(tx_Category,$J12))} -> Electronics | G12: {=IF($J12="","",INDEX(tx_Region,$J12))} -> East | H12: {=IF($J12="","",INDEX(tx_Qty,$J12))} -> 5 | I12: {=IF($J12="","",INDEX(tx_Total,$J12))} -> 4499.95 | J12: =IF($A12="","",MATCH($A12,$N$10:$N$259,0)) -> 51 | L12: =ROW()-ROW($L$9) -> 3 | M12: {=IF(AND(OR($B$3="All",INDEX(tx_Region,L12)=$B$3),OR($B$4="All",INDEX(tx_Category,L12)=$B$4),INDEX(tx_Total,L12)>=$B$5),1,0)} -> 0 | N12: =N11+M12 -> 0
A13: =IF(ROWS($A$10:A13)<=$B$6,ROWS($A$10:A13),"") -> 4 | B13: {=IF($J13="","",INDEX(tx_ID,$J13))} -> TRX0184 | C13: {=IF($J13="","",INDEX(tx_Date,$J13))} -> 45471 | D13: {=IF($J13="","",INDEX(tx_CustName,$J13))} -> Kathleen Bennett | E13: {=IF($J13="","",INDEX(tx_Product,$J13))} -> Smartphone | F13: {=IF($J13="","",INDEX(tx_Category,$J13))} -> Electronics | G13: {=IF($J13="","",INDEX(tx_Region,$J13))} -> East | H13: {=IF($J13="","",INDEX(tx_Qty,$J13))} -> 3 | I13: {=IF($J13="","",INDEX(tx_Total,$J13))} -> 2099.97 | J13: =IF($A13="","",MATCH($A13,$N$10:$N$259,0)) -> 57 | L13: =ROW()-ROW($L$9) -> 4 | M13: {=IF(AND(OR($B$3="All",INDEX(tx_Region,L13)=$B$3),OR($B$4="All",INDEX(tx_Category,L13)=$B$4),INDEX(tx_Total,L13)>=$B$5),1,0)} -> 0 | N13: =N12+M13 -> 0
A14: =IF(ROWS($A$10:A14)<=$B$6,ROWS($A$10:A14),"") -> 5 | B14: {=IF($J14="","",INDEX(tx_ID,$J14))} -> TRX0104 | C14: {=IF($J14="","",INDEX(tx_Date,$J14))} -> 45471 | D14: {=IF($J14="","",INDEX(tx_CustName,$J14))} -> Patricia Moore | E14: {=IF($J14="","",INDEX(tx_Product,$J14))} -> Laptop | F14: {=IF($J14="","",INDEX(tx_Category,$J14))} -> Electronics | G14: {=IF($J14="","",INDEX(tx_Region,$J14))} -> East | H14: {=IF($J14="","",INDEX(tx_Qty,$J14))} -> 4 | I14: {=IF($J14="","",INDEX(tx_Total,$J14))} -> 3599.96 | J14: =IF($A14="","",MATCH($A14,$N$10:$N$259,0)) -> 58 | L14: =ROW()-ROW($L$9) -> 5 | M14: {=IF(AND(OR($B$3="All",INDEX(tx_Region,L14)=$B$3),OR($B$4="All",INDEX(tx_Category,L14)=$B$4),INDEX(tx_Total,L14)>=$B$5),1,0)} -> 0 | N14: =N13+M14 -> 0
A15: =IF(ROWS($A$10:A15)<=$B$6,ROWS($A$10:A15),"") -> 6 | B15: {=IF($J15="","",INDEX(tx_ID,$J15))} -> TRX0132 | C15: {=IF($J15="","",INDEX(tx_Date,$J15))} -> 45523 | D15: {=IF($J15="","",INDEX(tx_CustName,$J15))} -> Gerald Murphy | E15: {=IF($J15="","",INDEX(tx_Product,$J15))} -> Laptop | F15: {=IF($J15="","",INDEX(tx_Category,$J15))} -> Electronics | G15: {=IF($J15="","",INDEX(tx_Region,$J15))} -> East | H15: {=IF($J15="","",INDEX(tx_Qty,$J15))} -> 5 | I15: {=IF($J15="","",INDEX(tx_Total,$J15))} -> 4499.95 | J15: =IF($A15="","",MATCH($A15,$N$10:$N$259,0)) -> 94 | L15: =ROW()-ROW($L$9) -> 6 | M15: {=IF(AND(OR($B$3="All",INDEX(tx_Region,L15)=$B$3),OR($B$4="All",INDEX(tx_Category,L15)=$B$4),INDEX(tx_Total,L15)>=$B$5),1,0)} -> 0 | N15: =N14+M15 -> 0
A16: =IF(ROWS($A$10:A16)<=$B$6,ROWS($A$10:A16),"") -> 7 | B16: {=IF($J16="","",INDEX(tx_ID,$J16))} -> TRX0173 | C16: {=IF($J16="","",INDEX(tx_Date,$J16))} -> 45581 | D16: {=IF($J16="","",INDEX(tx_CustName,$J16))} -> Barbara Young | E16: {=IF($J16="","",INDEX(tx_Product,$J16))} -> Smartphone | F16: {=IF($J16="","",INDEX(tx_Category,$J16))} -> Electronics | G16: {=IF($J16="","",INDEX(tx_Region,$J16))} -> East | H16: {=IF($J16="","",INDEX(tx_Qty,$J16))} -> 5 | I16: {=IF($J16="","",INDEX(tx_Total,$J16))} -> 3499.95 | J16: =IF($A16="","",MATCH($A16,$N$10:$N$259,0)) -> 128 | L16: =ROW()-ROW($L$9) -> 7 | M16: {=IF(AND(OR($B$3="All",INDEX(tx_Region,L16)=$B$3),OR($B$4="All",INDEX(tx_Category,L16)=$B$4),INDEX(tx_Total,L16)>=$B$5),1,0)} -> 0 | N16: =N15+M16 -> 0
A17: =IF(ROWS($A$10:A17)<=$B$6,ROWS($A$10:A17),"") -> 8 | B17: {=IF($J17="","",INDEX(tx_ID,$J17))} -> TRX0163 | C17: {=IF($J17="","",INDEX(tx_Date,$J17))} -> 45645 | D17: {=IF($J17="","",INDEX(tx_CustName,$J17))} -> Daniel King | E17: {=IF($J17="","",INDEX(tx_Product,$J17))} -> Laptop | F17: {=IF($J17="","",INDEX(tx_Category,$J17))} -> Electronics | G17: {=IF($J17="","",INDEX(tx_Region,$J17))} -> East | H17: {=IF($J17="","",INDEX(tx_Qty,$J17))} -> 5 | I17: {=IF($J17="","",INDEX(tx_Total,$J17))} -> 4499.95 | J17: =IF($A17="","",MATCH($A17,$N$10:$N$259,0)) -> 169 | L17: =ROW()-ROW($L$9) -> 8 | M17: {=IF(AND(OR($B$3="All",INDEX(tx_Region,L17)=$B$3),OR($B$4="All",INDEX(tx_Category,L17)=$B$4),INDEX(tx_Total,L17)>=$B$5),1,0)} -> 0 | N17: =N16+M17 -> 0
A18: =IF(ROWS($A$10:A18)<=$B$6,ROWS($A$10:A18),"") -> 9 | B18: {=IF($J18="","",INDEX(tx_ID,$J18))} -> TRX0214 | C18: {=IF($J18="","",INDEX(tx_Date,$J18))} -> 45708 | D18: {=IF($J18="","",INDEX(tx_CustName,$J18))} -> Barbara Young | E18: {=IF($J18="","",INDEX(tx_Product,$J18))} -> Laptop | F18: {=IF($J18="","",INDEX(tx_Category,$J18))} -> Electronics | G18: {=IF($J18="","",INDEX(tx_Region,$J18))} -> East | H18: {=IF($J18="","",INDEX(tx_Qty,$J18))} -> 3 | I18: {=IF($J18="","",INDEX(tx_Total,$J18))} -> 2699.97 | J18: =IF($A18="","",MATCH($A18,$N$10:$N$259,0)) -> 215 | L18: =ROW()-ROW($L$9) -> 9 | M18: {=IF(AND(OR($B$3="All",INDEX(tx_Region,L18)=$B$3),OR($B$4="All",INDEX(tx_Category,L18)=$B$4),INDEX(tx_Total,L18)>=$B$5),1,0)} -> 1 | N18: =N17+M18 -> 1
A19: =IF(ROWS($A$10:A19)<=$B$6,ROWS($A$10:A19),"") -> 10 | B19: {=IF($J19="","",INDEX(tx_ID,$J19))} -> TRX0226 | C19: {=IF($J19="","",INDEX(tx_Date,$J19))} -> 45720 | D19: {=IF($J19="","",INDEX(tx_CustName,$J19))} -> Lawrence Reed | E19: {=IF($J19="","",INDEX(tx_Product,$J19))} -> Smartphone | F19: {=IF($J19="","",INDEX(tx_Category,$J19))} -> Electronics | G19: {=IF($J19="","",INDEX(tx_Region,$J19))} -> East | H19: {=IF($J19="","",INDEX(tx_Qty,$J19))} -> 5 | I19: {=IF($J19="","",INDEX(tx_Total,$J19))} -> 3499.95 | J19: =IF($A19="","",MATCH($A19,$N$10:$N$259,0)) -> 226 | L19: =ROW()-ROW($L$9) -> 10 | M19: {=IF(AND(OR($B$3="All",INDEX(tx_Region,L19)=$B$3),OR($B$4="All",INDEX(tx_Category,L19)=$B$4),INDEX(tx_Total,L19)>=$B$5),1,0)} -> 0 | N19: =N18+M19 -> 1
A20: =IF(ROWS($A$10:A20)<=$B$6,ROWS($A$10:A20),"") -> 11 | B20: {=IF($J20="","",INDEX(tx_ID,$J20))} -> TRX0016 | C20: {=IF($J20="","",INDEX(tx_Date,$J20))} -> 45724 | D20: {=IF($J20="","",INDEX(tx_CustName,$J20))} -> Harry Morgan | E20: {=IF($J20="","",INDEX(tx_Product,$J20))} -> Laptop | F20: {=IF($J20="","",INDEX(tx_Category,$J20))} -> Electronics | G20: {=IF($J20="","",INDEX(tx_Region,$J20))} -> East | H20: {=IF($J20="","",INDEX(tx_Qty,$J20))} -> 5 | I20: {=IF($J20="","",INDEX(tx_Total,$J20))} -> 4499.95 | J20: =IF($A20="","",MATCH($A20,$N$10:$N$259,0)) -> 231 | L20: =ROW()-ROW($L$9) -> 11 | M20: {=IF(AND(OR($B$3="All",INDEX(tx_Region,L20)=$B$3),OR($B$4="All",INDEX(tx_Category,L20)=$B$4),INDEX(tx_Total,L20)>=$B$5),1,0)} -> 0 | N20: =N19+M20 -> 1
A21: =IF(ROWS($A$10:A21)<=$B$6,ROWS($A$10:A21),"") | B21: {=IF($J21="","",INDEX(tx_ID,$J21))} | C21: {=IF($J21="","",INDEX(tx_Date,$J21))} | D21: {=IF($J21="","",INDEX(tx_CustName,$J21))} | E21: {=IF($J21="","",INDEX(tx_Product,$J21))} | F21: {=IF($J21="","",INDEX(tx_Category,$J21))} | G21: {=IF($J21="","",INDEX(tx_Region,$J21))} | H21: {=IF($J21="","",INDEX(tx_Qty,$J21))} | I21: {=IF($J21="","",INDEX(tx_Total,$J21))} | J21: =IF($A21="","",MATCH($A21,$N$10:$N$259,0)) | L21: =ROW()-ROW($L$9) -> 12 | M21: {=IF(AND(OR($B$3="All",INDEX(tx_Region,L21)=$B$3),OR($B$4="All",INDEX(tx_Category,L21)=$B$4),INDEX(tx_Total,L21)>=$B$5),1,0)} -> 0 | N21: =N20+M21 -> 1
A22: =IF(ROWS($A$10:A22)<=$B$6,ROWS($A$10:A22),"") | B22: {=IF($J22="","",INDEX(tx_ID,$J22))} | C22: {=IF($J22="","",INDEX(tx_Date,$J22))} | D22: {=IF($J22="","",INDEX(tx_CustName,$J22))} | E22: {=IF($J22="","",INDEX(tx_Product,$J22))} | F22: {=IF($J22="","",INDEX(tx_Category,$J22))} | G22: {=IF($J22="","",INDEX(tx_Region,$J22))} | H22: {=IF($J22="","",INDEX(tx_Qty,$J22))} | I22: {=IF($J22="","",INDEX(tx_Total,$J22))} | J22: =IF($A22="","",MATCH($A22,$N$10:$N$259,0)) | L22: =ROW()-ROW($L$9) -> 13 | M22: {=IF(AND(OR($B$3="All",INDEX(tx_Region,L22)=$B$3),OR($B$4="All",INDEX(tx_Category,L22)=$B$4),INDEX(tx_Total,L22)>=$B$5),1,0)} -> 0 | N22: =N21+M22 -> 1
... A259: =IF(ROWS($A$10:A259)<=$B$6,ROWS($A$10:A259),"") | B259: {=IF($J259="","",INDEX(tx_ID,$J259))} | C259: {=IF($J259="","",INDEX(tx_Date,$J259))} | D259: {=IF($J259="","",INDEX(tx_CustName,$J259))} | E259: {=IF($J259="","",INDEX(tx_Product,$J259))} | F259: {=IF($J259="","",INDEX(tx_Category,$J259))} | G259: {=IF($J259="","",INDEX(tx_Region,$J259))} | H259: {=IF($J259="","",INDEX(tx_Qty,$J259))} | I259: {=IF($J259="","",INDEX(tx_Total,$J259))} | J259: =IF($A259="","",MATCH($A259,$N$10:$N$259,0)) | L259: =ROW()-ROW($L$9) -> 250 | M259: {=IF(AND(OR($B$3="All",INDEX(tx_Region,L259)=$B$3),OR($B$4="All",INDEX(tx_Category,L259)=$B$4),INDEX(tx_Total,L259)>=$B$5),1,0)} -> 0 | N259: =N258+M259 -> 11

Sheet Compare_Lists
A5: List A: Customers | B5: Match in list B | D5: List B: Loyalty Members | E5: Match in list A | F5: Matching name | G5: Revenue of match | I5: Match No | J5: list of matches | L5: Summary
A6: =Lists!H4 -> John Smith | B6: =IF(COUNTIF($D$6:$D$28,A6)>0,"Yes","No") -> No | D6: Mark Carter | E6: =IF(COUNTIF($A$6:$A$55,D6)>0,"Match","No match") -> Match | F6: =IF(E6="Match",D6,"") -> Mark Carter | G6: =IF(E6="Match",SUMIF(tx_CustName,D6,tx_Total),"") -> 15659.65 | I6: =IF(E6="Match",COUNTIF($E$6:E6,"Match"),"") -> 1 | J6: =IFERROR(INDEX($D$6:$D$28,MATCH(ROWS(J$6:J6),$I$6:$I$28,0)),"") -> Mark Carter | L6: Customers in List A | N6: =COUNTA(A6:A55) -> 50
A7: =Lists!H5 -> Emma Wilson | B7: =IF(COUNTIF($D$6:$D$28,A7)>0,"Yes","No") -> Yes | D7: Edward Mitchell | E7: =IF(COUNTIF($A$6:$A$55,D7)>0,"Match","No match") -> Match | F7: =IF(E7="Match",D7,"") -> Edward Mitchell | G7: =IF(E7="Match",SUMIF(tx_CustName,D7,tx_Total),"") -> 11919.77 | I7: =IF(E7="Match",COUNTIF($E$6:E7,"Match"),"") -> 2 | J7: =IFERROR(INDEX($D$6:$D$28,MATCH(ROWS(J$6:J7),$I$6:$I$28,0)),"") -> Edward Mitchell | L7: Names in List B | N7: =COUNTA(D6:D28) -> 23
A8: =Lists!H6 -> Michael Brown | B8: =IF(COUNTIF($D$6:$D$28,A8)>0,"Yes","No") -> Yes | D8: Barbara Young | E8: =IF(COUNTIF($A$6:$A$55,D8)>0,"Match","No match") -> Match | F8: =IF(E8="Match",D8,"") -> Barbara Young | G8: =IF(E8="Match",SUMIF(tx_CustName,D8,tx_Total),"") -> 10649.8 | I8: =IF(E8="Match",COUNTIF($E$6:E8,"Match"),"") -> 3 | J8: =IFERROR(INDEX($D$6:$D$28,MATCH(ROWS(J$6:J8),$I$6:$I$28,0)),"") -> Barbara Young | L8: Matches | N8: =COUNTIF(E6:E28,"Match") -> 18
A9: =Lists!H7 -> Sarah Davis | B9: =IF(COUNTIF($D$6:$D$28,A9)>0,"Yes","No") -> Yes | D9: Patricia Moore | E9: =IF(COUNTIF($A$6:$A$55,D9)>0,"Match","No match") -> Match | F9: =IF(E9="Match",D9,"") -> Patricia Moore | G9: =IF(E9="Match",SUMIF(tx_CustName,D9,tx_Total),"") -> 9799.73 | I9: =IF(E9="Match",COUNTIF($E$6:E9,"Match"),"") -> 4 | J9: =IFERROR(INDEX($D$6:$D$28,MATCH(ROWS(J$6:J9),$I$6:$I$28,0)),"") -> Patricia Moore | L9: Names only in List B | N9: =COUNTIF(E6:E28,"No match") -> 5
A10: =Lists!H8 -> James Johnson | B10: =IF(COUNTIF($D$6:$D$28,A10)>0,"Yes","No") -> No | D10: Paul Baker | E10: =IF(COUNTIF($A$6:$A$55,D10)>0,"Match","No match") -> Match | F10: =IF(E10="Match",D10,"") -> Paul Baker | G10: =IF(E10="Match",SUMIF(tx_CustName,D10,tx_Total),"") -> 8309.74 | I10: =IF(E10="Match",COUNTIF($E$6:E10,"Match"),"") -> 5 | J10: =IFERROR(INDEX($D$6:$D$28,MATCH(ROWS(J$6:J10),$I$6:$I$28,0)),"") -> Paul Baker | L10: Match rate | N10: =N8/N7 -> 0.7826087
A11: =Lists!H9 -> Lisa Anderson | B11: =IF(COUNTIF($D$6:$D$28,A11)>0,"Yes","No") -> Yes | D11: Dorothy Nelson | E11: =IF(COUNTIF($A$6:$A$55,D11)>0,"Match","No match") -> Match | F11: =IF(E11="Match",D11,"") -> Dorothy Nelson | G11: =IF(E11="Match",SUMIF(tx_CustName,D11,tx_Total),"") -> 8269.79 | I11: =IF(E11="Match",COUNTIF($E$6:E11,"Match"),"") -> 6 | J11: =IFERROR(INDEX($D$6:$D$28,MATCH(ROWS(J$6:J11),$I$6:$I$28,0)),"") -> Dorothy Nelson | L11: Revenue from loyalty members | N11: =SUM(G6:G28) -> 123326.35
A12: =Lists!H10 -> David Martinez | B12: =IF(COUNTIF($D$6:$D$28,A12)>0,"Yes","No") -> No | D12: Karen Hill | E12: =IF(COUNTIF($A$6:$A$55,D12)>0,"Match","No match") -> Match | F12: =IF(E12="Match",D12,"") -> Karen Hill | G12: =IF(E12="Match",SUMIF(tx_CustName,D12,tx_Total),"") -> 8009.77 | I12: =IF(E12="Match",COUNTIF($E$6:E12,"Match"),"") -> 7 | J12: =IFERROR(INDEX($D$6:$D$28,MATCH(ROWS(J$6:J12),$I$6:$I$28,0)),"") -> Karen Hill | L12: Share of total revenue | N12: =N11/SUM(tx_Total) -> 0.53809076
A13: =Lists!H11 -> Jennifer Taylor | B13: =IF(COUNTIF($D$6:$D$28,A13)>0,"Yes","No") -> No | D13: Daniel King | E13: =IF(COUNTIF($A$6:$A$55,D13)>0,"Match","No match") -> Match | F13: =IF(E13="Match",D13,"") -> Daniel King | G13: =IF(E13="Match",SUMIF(tx_CustName,D13,tx_Total),"") -> 7309.8 | I13: =IF(E13="Match",COUNTIF($E$6:E13,"Match"),"") -> 8 | J13: =IFERROR(INDEX($D$6:$D$28,MATCH(ROWS(J$6:J13),$I$6:$I$28,0)),"") -> Daniel King | L13: Customers not yet in loyalty list | N13: =COUNTIF(B6:B55,"No") -> 32
A14: =Lists!H12 -> Robert Thomas | B14: =IF(COUNTIF($D$6:$D$28,A14)>0,"Yes","No") -> Yes | D14: Lawrence Reed | E14: =IF(COUNTIF($A$6:$A$55,D14)>0,"Match","No match") -> Match | F14: =IF(E14="Match",D14,"") -> Lawrence Reed | G14: =IF(E14="Match",SUMIF(tx_CustName,D14,tx_Total),"") -> 6989.77 | I14: =IF(E14="Match",COUNTIF($E$6:E14,"Match"),"") -> 9 | J14: =IFERROR(INDEX($D$6:$D$28,MATCH(ROWS(J$6:J14),$I$6:$I$28,0)),"") -> Lawrence Reed
A15: =Lists!H13 -> Maria Garcia | B15: =IF(COUNTIF($D$6:$D$28,A15)>0,"Yes","No") -> No | D15: Joseph Jackson | E15: =IF(COUNTIF($A$6:$A$55,D15)>0,"Match","No match") -> Match | F15: =IF(E15="Match",D15,"") -> Joseph Jackson | G15: =IF(E15="Match",SUMIF(tx_CustName,D15,tx_Total),"") -> 6949.84 | I15: =IF(E15="Match",COUNTIF($E$6:E15,"Match"),"") -> 10 | J15: =IFERROR(INDEX($D$6:$D$28,MATCH(ROWS(J$6:J15),$I$6:$I$28,0)),"") -> Joseph Jackson
A16: =Lists!H14 -> William White | B16: =IF(COUNTIF($D$6:$D$28,A16)>0,"Yes","No") -> No | D16: Emma Wilson | E16: =IF(COUNTIF($A$6:$A$55,D16)>0,"Match","No match") -> Match | F16: =IF(E16="Match",D16,"") -> Emma Wilson | G16: =IF(E16="Match",SUMIF(tx_CustName,D16,tx_Total),"") -> 1229.88 | I16: =IF(E16="Match",COUNTIF($E$6:E16,"Match"),"") -> 11 | J16: =IFERROR(INDEX($D$6:$D$28,MATCH(ROWS(J$6:J16),$I$6:$I$28,0)),"") -> Emma Wilson
A17: =Lists!H15 -> Patricia Moore | B17: =IF(COUNTIF($D$6:$D$28,A17)>0,"Yes","No") -> Yes | D17: Rachel Adams | E17: =IF(COUNTIF($A$6:$A$55,D17)>0,"Match","No match") -> No match | F17: =IF(E17="Match",D17,"") | G17: =IF(E17="Match",SUMIF(tx_CustName,D17,tx_Total),"") | I17: =IF(E17="Match",COUNTIF($E$6:E17,"Match"),"") | J17: =IFERROR(INDEX($D$6:$D$28,MATCH(ROWS(J$6:J17),$I$6:$I$28,0)),"") -> Michael Brown
A18: =Lists!H16 -> Joseph Jackson | B18: =IF(COUNTIF($D$6:$D$28,A18)>0,"Yes","No") -> Yes | D18: Michael Brown | E18: =IF(COUNTIF($A$6:$A$55,D18)>0,"Match","No match") -> Match | F18: =IF(E18="Match",D18,"") -> Michael Brown | G18: =IF(E18="Match",SUMIF(tx_CustName,D18,tx_Total),"") -> 6169.74 | I18: =IF(E18="Match",COUNTIF($E$6:E18,"Match"),"") -> 12 | J18: =IFERROR(INDEX($D$6:$D$28,MATCH(ROWS(J$6:J18),$I$6:$I$28,0)),"") -> Sarah Davis
A19: =Lists!H17 -> Linda Martin | B19: =IF(COUNTIF($D$6:$D$28,A19)>0,"Yes","No") -> Yes | D19: Sarah Davis | E19: =IF(COUNTIF($A$6:$A$55,D19)>0,"Match","No match") -> Match | F19: =IF(E19="Match",D19,"") -> Sarah Davis | G19: =IF(E19="Match",SUMIF(tx_CustName,D19,tx_Total),"") -> 5499.81 | I19: =IF(E19="Match",COUNTIF($E$6:E19,"Match"),"") -> 13 | J19: =IFERROR(INDEX($D$6:$D$28,MATCH(ROWS(J$6:J19),$I$6:$I$28,0)),"") -> Linda Martin
A20: =Lists!H18 -> Richard Lee | B20: =IF(COUNTIF($D$6:$D$28,A20)>0,"Yes","No") -> No | D20: Oliver Grant | E20: =IF(COUNTIF($A$6:$A$55,D20)>0,"Match","No match") -> No match | F20: =IF(E20="Match",D20,"") | G20: =IF(E20="Match",SUMIF(tx_CustName,D20,tx_Total),"") | I20: =IF(E20="Match",COUNTIF($E$6:E20,"Match"),"") | J20: =IFERROR(INDEX($D$6:$D$28,MATCH(ROWS(J$6:J20),$I$6:$I$28,0)),"") -> Helen Roberts
A21: =Lists!H19 -> Elizabeth Hall | B21: =IF(COUNTIF($D$6:$D$28,A21)>0,"Yes","No") -> No | D21: Linda Martin | E21: =IF(COUNTIF($A$6:$A$55,D21)>0,"Match","No match") -> Match | F21: =IF(E21="Match",D21,"") -> Linda Martin | G21: =IF(E21="Match",SUMIF(tx_CustName,D21,tx_Total),"") -> 1289.9 | I21: =IF(E21="Match",COUNTIF($E$6:E21,"Match"),"") -> 14 | J21: =IFERROR(INDEX($D$6:$D$28,MATCH(ROWS(J$6:J21),$I$6:$I$28,0)),"") -> Kevin Scott
A22: =Lists!H20 -> Charles Allen | B22: =IF(COUNTIF($D$6:$D$28,A22)>0,"Yes","No") -> No | D22: Helen Roberts | E22: =IF(COUNTIF($A$6:$A$55,D22)>0,"Match","No match") -> Match | F22: =IF(E22="Match",D22,"") -> Helen Roberts | G22: =IF(E22="Match",SUMIF(tx_CustName,D22,tx_Total),"") -> 6459.79 | I22: =IF(E22="Match",COUNTIF($E$6:E22,"Match"),"") -> 15 | J22: =IFERROR(INDEX($D$6:$D$28,MATCH(ROWS(J$6:J22),$I$6:$I$28,0)),"") -> Robert Thomas
A23: =Lists!H21 -> Barbara Young | B23: =IF(COUNTIF($D$6:$D$28,A23)>0,"Yes","No") -> Yes | D23: Nina Patel | E23: =IF(COUNTIF($A$6:$A$55,D23)>0,"Match","No match") -> No match | F23: =IF(E23="Match",D23,"") | G23: =IF(E23="Match",SUMIF(tx_CustName,D23,tx_Total),"") | I23: =IF(E23="Match",COUNTIF($E$6:E23,"Match"),"") | J23: =IFERROR(INDEX($D$6:$D$28,MATCH(ROWS(J$6:J23),$I$6:$I$28,0)),"") -> Lisa Anderson
A24: =Lists!H22 -> Daniel King | B24: =IF(COUNTIF($D$6:$D$28,A24)>0,"Yes","No") -> Yes | D24: Kevin Scott | E24: =IF(COUNTIF($A$6:$A$55,D24)>0,"Match","No match") -> Match | F24: =IF(E24="Match",D24,"") -> Kevin Scott | G24: =IF(E24="Match",SUMIF(tx_CustName,D24,tx_Total),"") -> 3259.87 | I24: =IF(E24="Match",COUNTIF($E$6:E24,"Match"),"") -> 16 | J24: =IFERROR(INDEX($D$6:$D$28,MATCH(ROWS(J$6:J24),$I$6:$I$28,0)),"")
A25: =Lists!H23 -> Margaret Wright | B25: =IF(COUNTIF($D$6:$D$28,A25)>0,"Yes","No") -> No | D25: Victor Hughes | E25: =IF(COUNTIF($A$6:$A$55,D25)>0,"Match","No match") -> No match | F25: =IF(E25="Match",D25,"") | G25: =IF(E25="Match",SUMIF(tx_CustName,D25,tx_Total),"") | I25: =IF(E25="Match",COUNTIF($E$6:E25,"Match"),"") | J25: =IFERROR(INDEX($D$6:$D$28,MATCH(ROWS(J$6:J25),$I$6:$I$28,0)),"")
... A28: =Lists!H26 -> Paul Baker | B28: =IF(COUNTIF($D$6:$D$28,A28)>0,"Yes","No") -> Yes | D28: Lisa Anderson | E28: =IF(COUNTIF($A$6:$A$55,D28)>0,"Match","No match") -> Match | F28: =IF(E28="Match",D28,"") -> Lisa Anderson | G28: =IF(E28="Match",SUMIF(tx_CustName,D28,tx_Total),"") -> 2039.8 | I28: =IF(E28="Match",COUNTIF($E$6:E28,"Match"),"") -> 18 | J28: =IFERROR(INDEX($D$6:$D$28,MATCH(ROWS(J$6:J28),$I$6:$I$28,0)),"")
A29: =Lists!H27 -> Dorothy Nelson | B29: =IF(COUNTIF($D$6:$D$28,A29)>0,"Yes","No") -> Yes
A30: =Lists!H28 -> Mark Carter | B30: =IF(COUNTIF($D$6:$D$28,A30)>0,"Yes","No") -> Yes
A31: =Lists!H29 -> Karen Hill | B31: =IF(COUNTIF($D$6:$D$28,A31)>0,"Yes","No") -> Yes
A32: =Lists!H30 -> George Adams | B32: =IF(COUNTIF($D$6:$D$28,A32)>0,"Yes","No") -> No
A33: =Lists!H31 -> Betty Campbell | B33: =IF(COUNTIF($D$6:$D$28,A33)>0,"Yes","No") -> No
A34: =Lists!H32 -> Edward Mitchell | B34: =IF(COUNTIF($D$6:$D$28,A34)>0,"Yes","No") -> Yes
A35: =Lists!H33 -> Helen Roberts | B35: =IF(COUNTIF($D$6:$D$28,A35)>0,"Yes","No") -> Yes
A36: =Lists!H34 -> Steven Turner | B36: =IF(COUNTIF($D$6:$D$28,A36)>0,"Yes","No") -> No
A37: =Lists!H35 -> Sandra Phillips | B37: =IF(COUNTIF($D$6:$D$28,A37)>0,"Yes","No") -> No
A38: =Lists!H36 -> Frank Torres | B38: =IF(COUNTIF($D$6:$D$28,A38)>0,"Yes","No") -> No
A39: =Lists!H37 -> Carol Evans | B39: =IF(COUNTIF($D$6:$D$28,A39)>0,"Yes","No") -> No
A40: =Lists!H38 -> Harry Morgan | B40: =IF(COUNTIF($D$6:$D$28,A40)>0,"Yes","No") -> No
... A55: =Lists!H53 -> Julie Foster | B55: =IF(COUNTIF($D$6:$D$28,A55)>0,"Yes","No") -> No

Sheet Abbreviations
A2: Customer_ID | B2: Customer_Name | C2: First | D2: Last | E2: Initials | F2: Short Code | G2: Customer_Name | I2: Product | J2: Abbreviation | K2: Category | L2: Category Code
A3: =Lists!G4 -> CUST001 | B3: =Lists!H4 -> John Smith | C3: =LEFT(B3,FIND(" ",B3)-1) -> John | D3: =MID(B3,FIND(" ",B3)+1,50) -> Smith | E3: =UPPER(LEFT(C3,1)&LEFT(D3,1)) -> JS | F3: =UPPER(LEFT(C3,1)&LEFT(D3,3))&"-"&RIGHT(A3,3) -> JSMI-001 | G3: =D3&", "&LEFT(C3,1)&"." -> Smith, J. | I3: =Lists!D4 -> Laptop | J3: =IF(ISNUMBER(FIND(" ",I3)),UPPER(LEFT(I3,1)&MID(I3,FIND(" ",I3)+1,1)),UPPER(LEFT(I3,3))) -> LAP | K3: {=INDEX(tx_Category,MATCH(I3,tx_Product,0))} -> Electronics | L3: =UPPER(LEFT(K3,3)) -> ELE
A4: =Lists!G5 -> CUST002 | B4: =Lists!H5 -> Emma Wilson | C4: =LEFT(B4,FIND(" ",B4)-1) -> Emma | D4: =MID(B4,FIND(" ",B4)+1,50) -> Wilson | E4: =UPPER(LEFT(C4,1)&LEFT(D4,1)) -> EW | F4: =UPPER(LEFT(C4,1)&LEFT(D4,3))&"-"&RIGHT(A4,3) -> EWIL-002 | G4: =D4&", "&LEFT(C4,1)&"." -> Wilson, E. | I4: =Lists!D5 -> Smartphone | J4: =IF(ISNUMBER(FIND(" ",I4)),UPPER(LEFT(I4,1)&MID(I4,FIND(" ",I4)+1,1)),UPPER(LEFT(I4,3))) -> SMA | K4: {=INDEX(tx_Category,MATCH(I4,tx_Product,0))} -> Electronics | L4: =UPPER(LEFT(K4,3)) -> ELE
A5: =Lists!G6 -> CUST003 | B5: =Lists!H6 -> Michael Brown | C5: =LEFT(B5,FIND(" ",B5)-1) -> Michael | D5: =MID(B5,FIND(" ",B5)+1,50) -> Brown | E5: =UPPER(LEFT(C5,1)&LEFT(D5,1)) -> MB | F5: =UPPER(LEFT(C5,1)&LEFT(D5,3))&"-"&RIGHT(A5,3) -> MBRO-003 | G5: =D5&", "&LEFT(C5,1)&"." -> Brown, M. | I5: =Lists!D6 -> Headphones | J5: =IF(ISNUMBER(FIND(" ",I5)),UPPER(LEFT(I5,1)&MID(I5,FIND(" ",I5)+1,1)),UPPER(LEFT(I5,3))) -> HEA | K5: {=INDEX(tx_Category,MATCH(I5,tx_Product,0))} -> Electronics | L5: =UPPER(LEFT(K5,3)) -> ELE
A6: =Lists!G7 -> CUST004 | B6: =Lists!H7 -> Sarah Davis | C6: =LEFT(B6,FIND(" ",B6)-1) -> Sarah | D6: =MID(B6,FIND(" ",B6)+1,50) -> Davis | E6: =UPPER(LEFT(C6,1)&LEFT(D6,1)) -> SD | F6: =UPPER(LEFT(C6,1)&LEFT(D6,3))&"-"&RIGHT(A6,3) -> SDAV-004 | G6: =D6&", "&LEFT(C6,1)&"." -> Davis, S. | I6: =Lists!D7 -> Coffee Maker | J6: =IF(ISNUMBER(FIND(" ",I6)),UPPER(LEFT(I6,1)&MID(I6,FIND(" ",I6)+1,1)),UPPER(LEFT(I6,3))) -> CM | K6: {=INDEX(tx_Category,MATCH(I6,tx_Product,0))} -> Appliances | L6: =UPPER(LEFT(K6,3)) -> APP
A7: =Lists!G8 -> CUST005 | B7: =Lists!H8 -> James Johnson | C7: =LEFT(B7,FIND(" ",B7)-1) -> James | D7: =MID(B7,FIND(" ",B7)+1,50) -> Johnson | E7: =UPPER(LEFT(C7,1)&LEFT(D7,1)) -> JJ | F7: =UPPER(LEFT(C7,1)&LEFT(D7,3))&"-"&RIGHT(A7,3) -> JJOH-005 | G7: =D7&", "&LEFT(C7,1)&"." -> Johnson, J. | I7: =Lists!D8 -> Blender | J7: =IF(ISNUMBER(FIND(" ",I7)),UPPER(LEFT(I7,1)&MID(I7,FIND(" ",I7)+1,1)),UPPER(LEFT(I7,3))) -> BLE | K7: {=INDEX(tx_Category,MATCH(I7,tx_Product,0))} -> Appliances | L7: =UPPER(LEFT(K7,3)) -> APP
A8: =Lists!G9 -> CUST006 | B8: =Lists!H9 -> Lisa Anderson | C8: =LEFT(B8,FIND(" ",B8)-1) -> Lisa | D8: =MID(B8,FIND(" ",B8)+1,50) -> Anderson | E8: =UPPER(LEFT(C8,1)&LEFT(D8,1)) -> LA | F8: =UPPER(LEFT(C8,1)&LEFT(D8,3))&"-"&RIGHT(A8,3) -> LAND-006 | G8: =D8&", "&LEFT(C8,1)&"." -> Anderson, L. | I8: =Lists!D9 -> Office Chair | J8: =IF(ISNUMBER(FIND(" ",I8)),UPPER(LEFT(I8,1)&MID(I8,FIND(" ",I8)+1,1)),UPPER(LEFT(I8,3))) -> OC | K8: {=INDEX(tx_Category,MATCH(I8,tx_Product,0))} -> Furniture | L8: =UPPER(LEFT(K8,3)) -> FUR
A9: =Lists!G10 -> CUST007 | B9: =Lists!H10 -> David Martinez | C9: =LEFT(B9,FIND(" ",B9)-1) -> David | D9: =MID(B9,FIND(" ",B9)+1,50) -> Martinez | E9: =UPPER(LEFT(C9,1)&LEFT(D9,1)) -> DM | F9: =UPPER(LEFT(C9,1)&LEFT(D9,3))&"-"&RIGHT(A9,3) -> DMAR-007 | G9: =D9&", "&LEFT(C9,1)&"." -> Martinez, D. | I9: =Lists!D10 -> Desk | J9: =IF(ISNUMBER(FIND(" ",I9)),UPPER(LEFT(I9,1)&MID(I9,FIND(" ",I9)+1,1)),UPPER(LEFT(I9,3))) -> DES | K9: {=INDEX(tx_Category,MATCH(I9,tx_Product,0))} -> Furniture | L9: =UPPER(LEFT(K9,3)) -> FUR
A10: =Lists!G11 -> CUST008 | B10: =Lists!H11 -> Jennifer Taylor | C10: =LEFT(B10,FIND(" ",B10)-1) -> Jennifer | D10: =MID(B10,FIND(" ",B10)+1,50) -> Taylor | E10: =UPPER(LEFT(C10,1)&LEFT(D10,1)) -> JT | F10: =UPPER(LEFT(C10,1)&LEFT(D10,3))&"-"&RIGHT(A10,3) -> JTAY-008 | G10: =D10&", "&LEFT(C10,1)&"." -> Taylor, J. | I10: =Lists!D11 -> Bookshelf | J10: =IF(ISNUMBER(FIND(" ",I10)),UPPER(LEFT(I10,1)&MID(I10,FIND(" ",I10)+1,1)),UPPER(LEFT(I10,3))) -> BOO | K10: {=INDEX(tx_Category,MATCH(I10,tx_Product,0))} -> Furniture | L10: =UPPER(LEFT(K10,3)) -> FUR
A11: =Lists!G12 -> CUST009 | B11: =Lists!H12 -> Robert Thomas | C11: =LEFT(B11,FIND(" ",B11)-1) -> Robert | D11: =MID(B11,FIND(" ",B11)+1,50) -> Thomas | E11: =UPPER(LEFT(C11,1)&LEFT(D11,1)) -> RT | F11: =UPPER(LEFT(C11,1)&LEFT(D11,3))&"-"&RIGHT(A11,3) -> RTHO-009 | G11: =D11&", "&LEFT(C11,1)&"." -> Thomas, R. | I11: =Lists!D12 -> Monitor | J11: =IF(ISNUMBER(FIND(" ",I11)),UPPER(LEFT(I11,1)&MID(I11,FIND(" ",I11)+1,1)),UPPER(LEFT(I11,3))) -> MON | K11: {=INDEX(tx_Category,MATCH(I11,tx_Product,0))} -> Electronics | L11: =UPPER(LEFT(K11,3)) -> ELE
A12: =Lists!G13 -> CUST010 | B12: =Lists!H13 -> Maria Garcia | C12: =LEFT(B12,FIND(" ",B12)-1) -> Maria | D12: =MID(B12,FIND(" ",B12)+1,50) -> Garcia | E12: =UPPER(LEFT(C12,1)&LEFT(D12,1)) -> MG | F12: =UPPER(LEFT(C12,1)&LEFT(D12,3))&"-"&RIGHT(A12,3) -> MGAR-010 | G12: =D12&", "&LEFT(C12,1)&"." -> Garcia, M. | I12: =Lists!D13 -> Keyboard | J12: =IF(ISNUMBER(FIND(" ",I12)),UPPER(LEFT(I12,1)&MID(I12,FIND(" ",I12)+1,1)),UPPER(LEFT(I12,3))) -> KEY | K12: {=INDEX(tx_Category,MATCH(I12,tx_Product,0))} -> Electronics | L12: =UPPER(LEFT(K12,3)) -> ELE
A13: =Lists!G14 -> CUST011 | B13: =Lists!H14 -> William White | C13: =LEFT(B13,FIND(" ",B13)-1) -> William | D13: =MID(B13,FIND(" ",B13)+1,50) -> White | E13: =UPPER(LEFT(C13,1)&LEFT(D13,1)) -> WW | F13: =UPPER(LEFT(C13,1)&LEFT(D13,3))&"-"&RIGHT(A13,3) -> WWHI-011 | G13: =D13&", "&LEFT(C13,1)&"." -> White, W.
A14: =Lists!G15 -> CUST012 | B14: =Lists!H15 -> Patricia Moore | C14: =LEFT(B14,FIND(" ",B14)-1) -> Patricia | D14: =MID(B14,FIND(" ",B14)+1,50) -> Moore | E14: =UPPER(LEFT(C14,1)&LEFT(D14,1)) -> PM | F14: =UPPER(LEFT(C14,1)&LEFT(D14,3))&"-"&RIGHT(A14,3) -> PMOO-012 | G14: =D14&", "&LEFT(C14,1)&"." -> Moore, P.
A15: =Lists!G16 -> CUST013 | B15: =Lists!H16 -> Joseph Jackson | C15: =LEFT(B15,FIND(" ",B15)-1) -> Joseph | D15: =MID(B15,FIND(" ",B15)+1,50) -> Jackson | E15: =UPPER(LEFT(C15,1)&LEFT(D15,1)) -> JJ | F15: =UPPER(LEFT(C15,1)&LEFT(D15,3))&"-"&RIGHT(A15,3) -> JJAC-013 | G15: =D15&", "&LEFT(C15,1)&"." -> Jackson, J. | I15: Region | J15: Code
A16: =Lists!G17 -> CUST014 | B16: =Lists!H17 -> Linda Martin | C16: =LEFT(B16,FIND(" ",B16)-1) -> Linda | D16: =MID(B16,FIND(" ",B16)+1,50) -> Martin | E16: =UPPER(LEFT(C16,1)&LEFT(D16,1)) -> LM | F16: =UPPER(LEFT(C16,1)&LEFT(D16,3))&"-"&RIGHT(A16,3) -> LMAR-014 | G16: =D16&", "&LEFT(C16,1)&"." -> Martin, L. | I16: =Lists!A4 -> Central | J16: =UPPER(LEFT(I16,3)) -> CEN
A17: =Lists!G18 -> CUST015 | B17: =Lists!H18 -> Richard Lee | C17: =LEFT(B17,FIND(" ",B17)-1) -> Richard | D17: =MID(B17,FIND(" ",B17)+1,50) -> Lee | E17: =UPPER(LEFT(C17,1)&LEFT(D17,1)) -> RL | F17: =UPPER(LEFT(C17,1)&LEFT(D17,3))&"-"&RIGHT(A17,3) -> RLEE-015 | G17: =D17&", "&LEFT(C17,1)&"." -> Lee, R. | I17: =Lists!A5 -> East | J17: =UPPER(LEFT(I17,3)) -> EAS
A18: =Lists!G19 -> CUST016 | B18: =Lists!H19 -> Elizabeth Hall | C18: =LEFT(B18,FIND(" ",B18)-1) -> Elizabeth | D18: =MID(B18,FIND(" ",B18)+1,50) -> Hall | E18: =UPPER(LEFT(C18,1)&LEFT(D18,1)) -> EH | F18: =UPPER(LEFT(C18,1)&LEFT(D18,3))&"-"&RIGHT(A18,3) -> EHAL-016 | G18: =D18&", "&LEFT(C18,1)&"." -> Hall, E. | I18: =Lists!A6 -> North | J18: =UPPER(LEFT(I18,3)) -> NOR
A19: =Lists!G20 -> CUST017 | B19: =Lists!H20 -> Charles Allen | C19: =LEFT(B19,FIND(" ",B19)-1) -> Charles | D19: =MID(B19,FIND(" ",B19)+1,50) -> Allen | E19: =UPPER(LEFT(C19,1)&LEFT(D19,1)) -> CA | F19: =UPPER(LEFT(C19,1)&LEFT(D19,3))&"-"&RIGHT(A19,3) -> CALL-017 | G19: =D19&", "&LEFT(C19,1)&"." -> Allen, C. | I19: =Lists!A7 -> South | J19: =UPPER(LEFT(I19,3)) -> SOU
A20: =Lists!G21 -> CUST018 | B20: =Lists!H21 -> Barbara Young | C20: =LEFT(B20,FIND(" ",B20)-1) -> Barbara | D20: =MID(B20,FIND(" ",B20)+1,50) -> Young | E20: =UPPER(LEFT(C20,1)&LEFT(D20,1)) -> BY | F20: =UPPER(LEFT(C20,1)&LEFT(D20,3))&"-"&RIGHT(A20,3) -> BYOU-018 | G20: =D20&", "&LEFT(C20,1)&"." -> Young, B. | I20: =Lists!A8 -> West | J20: =UPPER(LEFT(I20,3)) -> WES
A21: =Lists!G22 -> CUST019 | B21: =Lists!H22 -> Daniel King | C21: =LEFT(B21,FIND(" ",B21)-1) -> Daniel | D21: =MID(B21,FIND(" ",B21)+1,50) -> King | E21: =UPPER(LEFT(C21,1)&LEFT(D21,1)) -> DK | F21: =UPPER(LEFT(C21,1)&LEFT(D21,3))&"-"&RIGHT(A21,3) -> DKIN-019 | G21: =D21&", "&LEFT(C21,1)&"." -> King, D.
A22: =Lists!G23 -> CUST020 | B22: =Lists!H23 -> Margaret Wright | C22: =LEFT(B22,FIND(" ",B22)-1) -> Margaret | D22: =MID(B22,FIND(" ",B22)+1,50) -> Wright | E22: =UPPER(LEFT(C22,1)&LEFT(D22,1)) -> MW | F22: =UPPER(LEFT(C22,1)&LEFT(D22,3))&"-"&RIGHT(A22,3) -> MWRI-020 | G22: =D22&", "&LEFT(C22,1)&"." -> Wright, M.
A23: =Lists!G24 -> CUST021 | B23: =Lists!H24 -> Kevin Scott | C23: =LEFT(B23,FIND(" ",B23)-1) -> Kevin | D23: =MID(B23,FIND(" ",B23)+1,50) -> Scott | E23: =UPPER(LEFT(C23,1)&LEFT(D23,1)) -> KS | F23: =UPPER(LEFT(C23,1)&LEFT(D23,3))&"-"&RIGHT(A23,3) -> KSCO-021 | G23: =D23&", "&LEFT(C23,1)&"." -> Scott, K. | I23: TEXT() example | J23: Result
A24: =Lists!G25 -> CUST022 | B24: =Lists!H25 -> Susan Green | C24: =LEFT(B24,FIND(" ",B24)-1) -> Susan | D24: =MID(B24,FIND(" ",B24)+1,50) -> Green | E24: =UPPER(LEFT(C24,1)&LEFT(D24,1)) -> SG | F24: =UPPER(LEFT(C24,1)&LEFT(D24,3))&"-"&RIGHT(A24,3) -> SGRE-022 | G24: =D24&", "&LEFT(C24,1)&"." -> Green, S. | I24: Last transaction date | J24: =TEXT(MAX(tx_Date),"dddd, dd mmmm yyyy") -> Friday, 11 April 2025
A25: =Lists!G26 -> CUST023 | B25: =Lists!H26 -> Paul Baker | C25: =LEFT(B25,FIND(" ",B25)-1) -> Paul | D25: =MID(B25,FIND(" ",B25)+1,50) -> Baker | E25: =UPPER(LEFT(C25,1)&LEFT(D25,1)) -> PB | F25: =UPPER(LEFT(C25,1)&LEFT(D25,3))&"-"&RIGHT(A25,3) -> PBAK-023 | G25: =D25&", "&LEFT(C25,1)&"." -> Baker, P. | I25: Total revenue | J25: =TEXT(SUM(tx_Total),"$#,##0.00") -> $229,192.47
A26: =Lists!G27 -> CUST024 | B26: =Lists!H27 -> Dorothy Nelson | C26: =LEFT(B26,FIND(" ",B26)-1) -> Dorothy | D26: =MID(B26,FIND(" ",B26)+1,50) -> Nelson | E26: =UPPER(LEFT(C26,1)&LEFT(D26,1)) -> DN | F26: =UPPER(LEFT(C26,1)&LEFT(D26,3))&"-"&RIGHT(A26,3) -> DNEL-024 | G26: =D26&", "&LEFT(C26,1)&"." -> Nelson, D. | I26: Electronics share | J26: =TEXT(Pivot_Summaries!F26,"0.0%") -> 74.9%
A27: =Lists!G28 -> CUST025 | B27: =Lists!H28 -> Mark Carter | C27: =LEFT(B27,FIND(" ",B27)-1) -> Mark | D27: =MID(B27,FIND(" ",B27)+1,50) -> Carter | E27: =UPPER(LEFT(C27,1)&LEFT(D27,1)) -> MC | F27: =UPPER(LEFT(C27,1)&LEFT(D27,3))&"-"&RIGHT(A27,3) -> MCAR-025 | G27: =D27&", "&LEFT(C27,1)&"." -> Carter, M. | I27: Today as month-year | J27: =TEXT(TODAY(),"mmm-yy") -> Sep-26
A28: =Lists!G29 -> CUST026 | B28: =Lists!H29 -> Karen Hill | C28: =LEFT(B28,FIND(" ",B28)-1) -> Karen | D28: =MID(B28,FIND(" ",B28)+1,50) -> Hill | E28: =UPPER(LEFT(C28,1)&LEFT(D28,1)) -> KH | F28: =UPPER(LEFT(C28,1)&LEFT(D28,3))&"-"&RIGHT(A28,3) -> KHIL-026 | G28: =D28&", "&LEFT(C28,1)&"." -> Hill, K.
A29: =Lists!G30 -> CUST027 | B29: =Lists!H30 -> George Adams | C29: =LEFT(B29,FIND(" ",B29)-1) -> George | D29: =MID(B29,FIND(" ",B29)+1,50) -> Adams | E29: =UPPER(LEFT(C29,1)&LEFT(D29,1)) -> GA | F29: =UPPER(LEFT(C29,1)&LEFT(D29,3))&"-"&RIGHT(A29,3) -> GADA-027 | G29: =D29&", "&LEFT(C29,1)&"." -> Adams, G.
A30: =Lists!G31 -> CUST028 | B30: =Lists!H31 -> Betty Campbell | C30: =LEFT(B30,FIND(" ",B30)-1) -> Betty | D30: =MID(B30,FIND(" ",B30)+1,50) -> Campbell | E30: =UPPER(LEFT(C30,1)&LEFT(D30,1)) -> BC | F30: =UPPER(LEFT(C30,1)&LEFT(D30,3))&"-"&RIGHT(A30,3) -> BCAM-028 | G30: =D30&", "&LEFT(C30,1)&"." -> Campbell, B.
A31: =Lists!G32 -> CUST029 | B31: =Lists!H32 -> Edward Mitchell | C31: =LEFT(B31,FIND(" ",B31)-1) -> Edward | D31: =MID(B31,FIND(" ",B31)+1,50) -> Mitchell | E31: =UPPER(LEFT(C31,1)&LEFT(D31,1)) -> EM | F31: =UPPER(LEFT(C31,1)&LEFT(D31,3))&"-"&RIGHT(A31,3) -> EMIT-029 | G31: =D31&", "&LEFT(C31,1)&"." -> Mitchell, E.
A32: =Lists!G33 -> CUST030 | B32: =Lists!H33 -> Helen Roberts | C32: =LEFT(B32,FIND(" ",B32)-1) -> Helen | D32: =MID(B32,FIND(" ",B32)+1,50) -> Roberts | E32: =UPPER(LEFT(C32,1)&LEFT(D32,1)) -> HR | F32: =UPPER(LEFT(C32,1)&LEFT(D32,3))&"-"&RIGHT(A32,3) -> HROB-030 | G32: =D32&", "&LEFT(C32,1)&"." -> Roberts, H.
A33: =Lists!G34 -> CUST031 | B33: =Lists!H34 -> Steven Turner | C33: =LEFT(B33,FIND(" ",B33)-1) -> Steven | D33: =MID(B33,FIND(" ",B33)+1,50) -> Turner | E33: =UPPER(LEFT(C33,1)&LEFT(D33,1)) -> ST | F33: =UPPER(LEFT(C33,1)&LEFT(D33,3))&"-"&RIGHT(A33,3) -> STUR-031 | G33: =D33&", "&LEFT(C33,1)&"." -> Turner, S.
A34: =Lists!G35 -> CUST032 | B34: =Lists!H35 -> Sandra Phillips | C34: =LEFT(B34,FIND(" ",B34)-1) -> Sandra | D34: =MID(B34,FIND(" ",B34)+1,50) -> Phillips | E34: =UPPER(LEFT(C34,1)&LEFT(D34,1)) -> SP | F34: =UPPER(LEFT(C34,1)&LEFT(D34,3))&"-"&RIGHT(A34,3) -> SPHI-032 | G34: =D34&", "&LEFT(C34,1)&"." -> Phillips, S.
A35: =Lists!G36 -> CUST033 | B35: =Lists!H36 -> Frank Torres | C35: =LEFT(B35,FIND(" ",B35)-1) -> Frank | D35: =MID(B35,FIND(" ",B35)+1,50) -> Torres | E35: =UPPER(LEFT(C35,1)&LEFT(D35,1)) -> FT | F35: =UPPER(LEFT(C35,1)&LEFT(D35,3))&"-"&RIGHT(A35,3) -> FTOR-033 | G35: =D35&", "&LEFT(C35,1)&"." -> Torres, F.
A36: =Lists!G37 -> CUST034 | B36: =Lists!H37 -> Carol Evans | C36: =LEFT(B36,FIND(" ",B36)-1) -> Carol | D36: =MID(B36,FIND(" ",B36)+1,50) -> Evans | E36: =UPPER(LEFT(C36,1)&LEFT(D36,1)) -> CE | F36: =UPPER(LEFT(C36,1)&LEFT(D36,3))&"-"&RIGHT(A36,3) -> CEVA-034 | G36: =D36&", "&LEFT(C36,1)&"." -> Evans, C.
A37: =Lists!G38 -> CUST035 | B37: =Lists!H38 -> Harry Morgan | C37: =LEFT(B37,FIND(" ",B37)-1) -> Harry | D37: =MID(B37,FIND(" ",B37)+1,50) -> Morgan | E37: =UPPER(LEFT(C37,1)&LEFT(D37,1)) -> HM | F37: =UPPER(LEFT(C37,1)&LEFT(D37,3))&"-"&RIGHT(A37,3) -> HMOR-035 | G37: =D37&", "&LEFT(C37,1)&"." -> Morgan, H.
A38: =Lists!G39 -> CUST036 | B38: =Lists!H39 -> Nancy Collins | C38: =LEFT(B38,FIND(" ",B38)-1) -> Nancy | D38: =MID(B38,FIND(" ",B38)+1,50) -> Collins | E38: =UPPER(LEFT(C38,1)&LEFT(D38,1)) -> NC | F38: =UPPER(LEFT(C38,1)&LEFT(D38,3))&"-"&RIGHT(A38,3) -> NCOL-036 | G38: =D38&", "&LEFT(C38,1)&"." -> Collins, N.
A39: =Lists!G40 -> CUST037 | B39: =Lists!H40 -> Arthur Edwards | C39: =LEFT(B39,FIND(" ",B39)-1) -> Arthur | D39: =MID(B39,FIND(" ",B39)+1,50) -> Edwards | E39: =UPPER(LEFT(C39,1)&LEFT(D39,1)) -> AE | F39: =UPPER(LEFT(C39,1)&LEFT(D39,3))&"-"&RIGHT(A39,3) -> AEDW-037 | G39: =D39&", "&LEFT(C39,1)&"." -> Edwards, A.
... A52: =Lists!G53 -> CUST050 | B52: =Lists!H53 -> Julie Foster | C52: =LEFT(B52,FIND(" ",B52)-1) -> Julie | D52: =MID(B52,FIND(" ",B52)+1,50) -> Foster | E52: =UPPER(LEFT(C52,1)&LEFT(D52,1)) -> JF | F52: =UPPER(LEFT(C52,1)&LEFT(D52,3))&"-"&RIGHT(A52,3) -> JFOS-050 | G52: =D52&", "&LEFT(C52,1)&"." -> Foster, J.

Sheet What_If
A3: Baseline data
A4: Baseline revenue | B4: =SUM(tx_Total) -> 229192.47
A5: Baseline units | B5: =SUM(tx_Qty) -> 753
A6: Average revenue per unit | B6: =B4/B5 -> 304.37247
A8: Scenario Manager
A9: Scenario | B9: Price change % | C9: Volume change % | D9: Projected Revenue | E9: vs Baseline | F9: vs Baseline
A10: Pessimistic | B10: -0.05 | C10: -0.1 | D10: =$B$4*(1+B10)*(1+C10) -> 195959.56 | E10: =D10-$B$4 -> -33232.908 | F10: =E10/$B$4 -> -0.145
A11: Base | B11: 0 | C11: 0 | D11: =$B$4*(1+B11)*(1+C11) -> 229192.47 | E11: =D11-$B$4 -> 0 | F11: =E11/$B$4 -> 0
A12: Optimistic | B12: 0.05 | C12: 0.1 | D12: =$B$4*(1+B12)*(1+C12) -> 264717.3 | E12: =D12-$B$4 -> 35524.833 | F12: =E12/$B$4 -> 0.155
A14: Active scenario (pick one) | B14: Optimistic
A15: Price change | B15: {=INDEX(B10:B12,MATCH(B14,A10:A12,0))} -> 0.05
A16: Volume change | B16: {=INDEX(C10:C12,MATCH(B14,A10:A12,0))} -> 0.1
A17: Projected revenue | B17: =$B$4*(1+B15)*(1+B16) -> 264717.3
A19: Category | B19: Baseline Revenue | C19: Projected (active scenario) | D19: Change
A20: =Lists!B4 -> Appliances | B20: =SUMIFS(tx_Total,tx_Category,A20) -> 8338.74 | C20: =B20*(1+$B$15)*(1+$B$16) -> 9631.2447 | D20: =C20-B20 -> 1292.5047
A21: =Lists!B5 -> Electronics | B21: =SUMIFS(tx_Total,tx_Category,A21) -> 171756.05 | C21: =B21*(1+$B$15)*(1+$B$16) -> 198378.24 | D21: =C21-B21 -> 26622.188
A22: =Lists!B6 -> Furniture | B22: =SUMIFS(tx_Total,tx_Category,A22) -> 49097.68 | C22: =B22*(1+$B$15)*(1+$B$16) -> 56707.82 | D22: =C22-B22 -> 7610.1404
A23: Total | B23: =SUM(B20:B22) -> 229192.47 | C23: =SUM(C20:C22) -> 264717.3 | D23: =SUM(D20:D22) -> 35524.833
A26: Goal Seek set-up
A27: Target revenue | B27: 250000
A28: Volume change held constant | B28: 0
A29: Price change % | B29: 0
A30: Model revenue | B30: =$B$4*(1+B29)*(1+B28) -> 229192.47
A31: Gap to target | B31: =B27-B30 -> 20807.53
A32: Goal Seek answer | B32: =B27/($B$4*(1+B28))-1 -> 0.090786272
A33: Check: revenue at that price change | B33: =$B$4*(1+B32)*(1+B28) -> 250000
A34: Check: difference to target | B34: =ROUND(B33-B27,2) -> 0
A35: Units needed at current avg price/unit | B35: =B27/B6 -> 821.36206
A36: Extra units vs baseline | B36: =B35-B5 -> 68.362063
A40: Projected revenue
B41: Volume change
B42: -0.1 | C42: -0.05 | D42: 0 | E42: 0.05 | F42: 0.1
A43: -0.1 | B43: =$B$4*(1+$A43)*(1+B$42) -> 185645.9 | C43: =$B$4*(1+$A43)*(1+C$42) -> 195959.56 | D43: =$B$4*(1+$A43)*(1+D$42) -> 206273.22 | E43: =$B$4*(1+$A43)*(1+E$42) -> 216586.88 | F43: =$B$4*(1+$A43)*(1+F$42) -> 226900.55 | G43: Price change
A44: -0.05 | B44: =$B$4*(1+$A44)*(1+B$42) -> 195959.56 | C44: =$B$4*(1+$A44)*(1+C$42) -> 206846.2 | D44: =$B$4*(1+$A44)*(1+D$42) -> 217732.85 | E44: =$B$4*(1+$A44)*(1+E$42) -> 228619.49 | F44: =$B$4*(1+$A44)*(1+F$42) -> 239506.13
A45: 0 | B45: =$B$4*(1+$A45)*(1+B$42) -> 206273.22 | C45: =$B$4*(1+$A45)*(1+C$42) -> 217732.85 | D45: =$B$4*(1+$A45)*(1+D$42) -> 229192.47 | E45: =$B$4*(1+$A45)*(1+E$42) -> 240652.09 | F45: =$B$4*(1+$A45)*(1+F$42) -> 252111.72
A46: 0.05 | B46: =$B$4*(1+$A46)*(1+B$42) -> 216586.88 | C46: =$B$4*(1+$A46)*(1+C$42) -> 228619.49 | D46: =$B$4*(1+$A46)*(1+D$42) -> 240652.09 | E46: =$B$4*(1+$A46)*(1+E$42) -> 252684.7 | F46: =$B$4*(1+$A46)*(1+F$42) -> 264717.3
A47: 0.1 | B47: =$B$4*(1+$A47)*(1+B$42) -> 226900.55 | C47: =$B$4*(1+$A47)*(1+C$42) -> 239506.13 | D47: =$B$4*(1+$A47)*(1+D$42) -> 252111.72 | E47: =$B$4*(1+$A47)*(1+E$42) -> 264717.3 | F47: =$B$4*(1+$A47)*(1+F$42) -> 277322.89

Sheet Regression
B4: Month | C4: Revenue | E4: Regression Statistics | F4: Value
A5: =ROWS($A$5:A5) -> 1 | B5: =Pivot_Summaries!J6 -> 45413 | C5: =Pivot_Summaries!L6 -> 17039.35 | E5: Multiple R | F5: =SQRT(F6) -> 0.27649117
A6: =ROWS($A$5:A6) -> 2 | B6: =Pivot_Summaries!J7 -> 45444 | C6: =Pivot_Summaries!L7 -> 19299.45 | E6: R Square | F6: =RSQ($C$5:$C$15,$A$5:$A$15) -> 0.076447365
A7: =ROWS($A$5:A7) -> 3 | B7: =Pivot_Summaries!J8 -> 45474 | C7: =Pivot_Summaries!L8 -> 18479.4 | E7: Adjusted R Square | F7: =1-(1-F6)*(F9-1)/(F9-2) -> -0.026169594
A8: =ROWS($A$5:A8) -> 4 | B8: =Pivot_Summaries!J9 -> 45505 | C8: =Pivot_Summaries!L9 -> 15759.43 | E8: Standard Error | F8: =STEYX($C$5:$C$15,$A$5:$A$15) -> 4111.4425
A9: =ROWS($A$5:A9) -> 5 | B9: =Pivot_Summaries!J10 -> 45536 | C9: =Pivot_Summaries!L10 -> 12989.51 | E9: Observations | F9: =COUNT($C$5:$C$15) -> 11
A10: =ROWS($A$5:A10) -> 6 | B10: =Pivot_Summaries!J11 -> 45566 | C10: =Pivot_Summaries!L11 -> 20609.52
A11: =ROWS($A$5:A11) -> 7 | B11: =Pivot_Summaries!J12 -> 45597 | C11: =Pivot_Summaries!L12 -> 12309.44 | E11: ANOVA | F11: df | G11: SS | H11: MS | I11: F | J11: Significance F
A12: =ROWS($A$5:A12) -> 8 | B12: =Pivot_Summaries!J13 -> 45627 | C12: =Pivot_Summaries!L13 -> 23039.3 | E12: Regression | F12: 1 | G12: {=INDEX(LINEST($C$5:$C$15,$A$5:$A$15,TRUE(),TRUE()),5,1)} -> 12593076 | H12: =G12/F12 -> 12593076 | I12: =H12/H13 -> 0.74497788 | J12: =FDIST(I12,F12,F13) -> 0.41048135
A13: =ROWS($A$5:A13) -> 9 | B13: =Pivot_Summaries!J14 -> 45658 | C13: =Pivot_Summaries!L14 -> 25799.15 | E13: Residual | F13: =F9-2 -> 9 | G13: {=INDEX(LINEST($C$5:$C$15,$A$5:$A$15,TRUE(),TRUE()),5,2)} -> 1.5213563e+08 | H13: =G13/F13 -> 16903959
A14: =ROWS($A$5:A14) -> 10 | B14: =Pivot_Summaries!J15 -> 45689 | C14: =Pivot_Summaries!L15 -> 16069.38 | E14: Total | F14: =F9-1 -> 10 | G14: =G12+G13 -> 1.6472871e+08
A15: =ROWS($A$5:A15) -> 11 | B15: =Pivot_Summaries!J16 -> 45717 | C15: =Pivot_Summaries!L16 -> 19899.38
F16: Coefficients | G16: Standard Error | H16: t Stat | I16: P-value | J16: Lower 95% | K16: Upper 95%
E17: Intercept | F17: {=INDEX(LINEST($C$5:$C$15,$A$5:$A$15,TRUE(),TRUE()),1,2)} -> 16269.276 | G17: {=INDEX(LINEST($C$5:$C$15,$A$5:$A$15,TRUE(),TRUE()),2,2)} -> 2658.7456 | H17: =F17/G17 -> 6.1191548 | I17: =TDIST(ABS(H17),$F$13,2) -> 0.00017513081 | J17: =F17-TINV(0.05,$F$13)*G17 -> 10254.776 | K17: =F17+TINV(0.05,$F$13)*G17 -> 22283.776
E18: Month index (slope) | F18: {=INDEX(LINEST($C$5:$C$15,$A$5:$A$15,TRUE(),TRUE()),1,1)} -> 338.35264 | G18: {=INDEX(LINEST($C$5:$C$15,$A$5:$A$15,TRUE(),TRUE()),2,1)} -> 392.01066 | H18: =F18/G18 -> 0.86312101 | I18: =TDIST(ABS(H18),$F$13,2) -> 0.41048135 | J18: =F18-TINV(0.05,$F$13)*G18 -> -548.43708 | K18: =F18+TINV(0.05,$F$13)*G18 -> 1225.1424
E20: Cross-check SLOPE() | F20: =SLOPE($C$5:$C$15,$A$5:$A$15) -> 338.35264
E21: Cross-check INTERCEPT() | F21: =INTERCEPT($C$5:$C$15,$A$5:$A$15) -> 16269.276
E26: t | F26: Month | G26: Forecast Revenue
E27: =$F$9+1 -> 12 | F27: =EDATE($B$15,1) -> 45748 | G27: =$F$17+$F$18*E27 -> 20329.508
E28: =$F$9+2 -> 13 | F28: =EDATE($B$15,2) -> 45778 | G28: =$F$17+$F$18*E28 -> 20667.86
E29: =$F$9+3 -> 14 | F29: =EDATE($B$15,3) -> 45809 | G29: =$F$17+$F$18*E29 -> 21006.213

Sheet Visualizations

Sheet Dashboard
P3: Month | Q3: Revenue | S3: Product | T3: Revenue | V3: Customer_ID | W3: Name | X3: Revenue | Y3: Rank
B4: Region ▸ | C4: All | E4: Category ▸ | F4: All | P4: =Pivot_Summaries!Q5 -> Apr-24 | Q4: =SUMIFS(tx_Total,tx_Date,">="&Pivot_Summaries!J5,tx_Date,"<="&Pivot_Summaries!K5,tx_Region,$L$5,tx_Category,$M$5) -> 20919.33 | S4: =Lists!D4 -> Laptop | T4: =SUMIFS(tx_Total,tx_Product,S4,tx_Region,$L$5,tx_Category,$M$5) -> 67499.25 | V4: =Lists!G4 -> CUST001 | W4: =Lists!H4 -> John Smith | X4: =SUMIFS(tx_Total,tx_CustID,V4,tx_Region,$L$5,tx_Category,$M$5) -> 599.96 | Y4: =RANK(X4,$X$4:$X$53,0)+COUNTIF($X$4:X4,X4)-1 -> 47
K5: criteria: | L5: =IF(C4="All","*",C4) -> * | M5: =IF(F4="All","*",F4) -> * | P5: =Pivot_Summaries!Q6 -> May-24 | Q5: =SUMIFS(tx_Total,tx_Date,">="&Pivot_Summaries!J6,tx_Date,"<="&Pivot_Summaries!K6,tx_Region,$L$5,tx_Category,$M$5) -> 17039.35 | S5: =Lists!D5 -> Smartphone | T5: =SUMIFS(tx_Total,tx_Product,S5,tx_Region,$L$5,tx_Category,$M$5) -> 67199.04 | V5: =Lists!G5 -> CUST002 | W5: =Lists!H5 -> Emma Wilson | X5: =SUMIFS(tx_Total,tx_CustID,V5,tx_Region,$L$5,tx_Category,$M$5) -> 1229.88 | Y5: =RANK(X5,$X$4:$X$53,0)+COUNTIF($X$4:X5,X5)-1 -> 44
P6: =Pivot_Summaries!Q7 -> Jun-24 | Q6: =SUMIFS(tx_Total,tx_Date,">="&Pivot_Summaries!J7,tx_Date,"<="&Pivot_Summaries!K7,tx_Region,$L$5,tx_Category,$M$5) -> 19299.45 | S6: =Lists!D6 -> Headphones | T6: =SUMIFS(tx_Total,tx_Product,S6,tx_Region,$L$5,tx_Category,$M$5) -> 7049.53 | V6: =Lists!G6 -> CUST003 | W6: =Lists!H6 -> Michael Brown | X6: =SUMIFS(tx_Total,tx_CustID,V6,tx_Region,$L$5,tx_Category,$M$5) -> 6169.74 | Y6: =RANK(X6,$X$4:$X$53,0)+COUNTIF($X$4:X6,X6)-1 -> 14
B7: TOTAL REVENUE | D7: TRANSACTIONS | F7: UNITS SOLD | H7: AVG ORDER VALUE | J7: MoM GROWTH | L7: TOP PRODUCT | P7: =Pivot_Summaries!Q8 -> Jul-24 | Q7: =SUMIFS(tx_Total,tx_Date,">="&Pivot_Summaries!J8,tx_Date,"<="&Pivot_Summaries!K8,tx_Region,$L$5,tx_Category,$M$5) -> 18479.4 | S7: =Lists!D7 -> Coffee Maker | T7: =SUMIFS(tx_Total,tx_Product,S7,tx_Region,$L$5,tx_Category,$M$5) -> 3119.61 | V7: =Lists!G7 -> CUST004 | W7: =Lists!H7 -> Sarah Davis | X7: =SUMIFS(tx_Total,tx_CustID,V7,tx_Region,$L$5,tx_Category,$M$5) -> 5499.81 | Y7: =RANK(X7,$X$4:$X$53,0)+COUNTIF($X$4:X7,X7)-1 -> 19
B8: =SUMIFS(tx_Total,tx_Region,$L$5,tx_Category,$M$5) -> 229192.47 | D8: =COUNTIFS(tx_Region,$L$5,tx_Category,$M$5) -> 250 | F8: =SUMIFS(tx_Qty,tx_Region,$L$5,tx_Category,$M$5) -> 753 | H8: =IF(D8=0,0,B8/D8) -> 916.76988 | J8: =IFERROR(SUMIFS(tx_Total,tx_Date,">="&Pivot_Summaries!$J$16,tx_Date,"<="&Pivot_Summaries!$K$16,tx_Region,$L$5,tx_Category,$M$5)/SUMIFS(tx_Total,tx_Date,">="&Pivot_Summaries!$J$15,tx_Date,"<="&Pivot_Summaries!$K$15,tx_Region,$L$5,tx_Category,$M$5)-1,0) -> 0.23834149 | L8: {=INDEX($S$4:$S$13,MATCH(MAX($T$4:$T$13),$T$4:$T$13,0))} -> Laptop | P8: =Pivot_Summaries!Q9 -> Aug-24 | Q8: =SUMIFS(tx_Total,tx_Date,">="&Pivot_Summaries!J9,tx_Date,"<="&Pivot_Summaries!K9,tx_Region,$L$5,tx_Category,$M$5) -> 15759.43 | S8: =Lists!D8 -> Blender | T8: =SUMIFS(tx_Total,tx_Product,S8,tx_Region,$L$5,tx_Category,$M$5) -> 5219.13 | V8: =Lists!G8 -> CUST005 | W8: =Lists!H8 -> James Johnson | X8: =SUMIFS(tx_Total,tx_CustID,V8,tx_Region,$L$5,tx_Category,$M$5) -> 179.97 | Y8: =RANK(X8,$X$4:$X$53,0)+COUNTIF($X$4:X8,X8)-1 -> 50
B9: =TEXT(B8/SUM(tx_Total),"0.0%")&" of total revenue" -> 100.0% of total revenue | D9: =TEXT(D8/COUNTA(tx_ID),"0.0%")&" of all transactions" -> 100.0% of all transactions | F9: ="avg "&TEXT(IF(D8=0,0,F8/D8),"0.0")&" units per order" -> avg 3.0 units per order | H9: ="overall: "&TEXT(SUM(tx_Total)/COUNTA(tx_ID),"$#,##0") -> overall: $917 | J9: =TEXT(Pivot_Summaries!$J$16,"mmm-yy")&" vs "&TEXT(Pivot_Summaries!$J$15,"mmm-yy") -> Mar-25 vs Feb-25 | L9: ="revenue "&TEXT(MAX($T$4:$T$13),"$#,##0") -> revenue $67,499 | P9: =Pivot_Summaries!Q10 -> Sep-24 | Q9: =SUMIFS(tx_Total,tx_Date,">="&Pivot_Summaries!J10,tx_Date,"<="&Pivot_Summaries!K10,tx_Region,$L$5,tx_Category,$M$5) -> 12989.51 | S9: =Lists!D9 -> Office Chair | T9: =SUMIFS(tx_Total,tx_Product,S9,tx_Region,$L$5,tx_Category,$M$5) -> 10399.48 | V9: =Lists!G9 -> CUST006 | W9: =Lists!H9 -> Lisa Anderson | X9: =SUMIFS(tx_Total,tx_CustID,V9,tx_Region,$L$5,tx_Category,$M$5) -> 2039.8 | Y9: =RANK(X9,$X$4:$X$53,0)+COUNTIF($X$4:X9,X9)-1 -> 36
P10: =Pivot_Summaries!Q11 -> Oct-24 | Q10: =SUMIFS(tx_Total,tx_Date,">="&Pivot_Summaries!J11,tx_Date,"<="&Pivot_Summaries!K11,tx_Region,$L$5,tx_Category,$M$5) -> 20609.52 | S10: =Lists!D10 -> Desk | T10: =SUMIFS(tx_Total,tx_Product,S10,tx_Region,$L$5,tx_Category,$M$5) -> 23399.22 | V10: =Lists!G10 -> CUST007 | W10: =Lists!H10 -> David Martinez | X10: =SUMIFS(tx_Total,tx_CustID,V10,tx_Region,$L$5,tx_Category,$M$5) -> 1809.84 | Y10: =RANK(X10,$X$4:$X$53,0)+COUNTIF($X$4:X10,X10)-1 -> 39
B11: KPI Scorecard | H11: Revenue by Region | P11: =Pivot_Summaries!Q12 -> Nov-24 | Q11: =SUMIFS(tx_Total,tx_Date,">="&Pivot_Summaries!J12,tx_Date,"<="&Pivot_Summaries!K12,tx_Region,$L$5,tx_Category,$M$5) -> 12309.44 | S11: =Lists!D11 -> Bookshelf | T11: =SUMIFS(tx_Total,tx_Product,S11,tx_Region,$L$5,tx_Category,$M$5) -> 15298.98 | V11: =Lists!G11 -> CUST008 | W11: =Lists!H11 -> Jennifer Taylor | X11: =SUMIFS(tx_Total,tx_CustID,V11,tx_Region,$L$5,tx_Category,$M$5) -> 4739.85 | Y11: =RANK(X11,$X$4:$X$53,0)+COUNTIF($X$4:X11,X11)-1 -> 24
B12: KPI | C12: Actual | D12: Target | E12: Attainment | H12: Region | I12: Revenue | J12: Share | K12: vs Avg Region | P12: =Pivot_Summaries!Q13 -> Dec-24 | Q12: =SUMIFS(tx_Total,tx_Date,">="&Pivot_Summaries!J13,tx_Date,"<="&Pivot_Summaries!K13,tx_Region,$L$5,tx_Category,$M$5) -> 23039.3 | S12: =Lists!D12 -> Monitor | T12: =SUMIFS(tx_Total,tx_Product,S12,tx_Region,$L$5,tx_Category,$M$5) -> 21999.12 | V12: =Lists!G12 -> CUST009 | W12: =Lists!H12 -> Robert Thomas | X12: =SUMIFS(tx_Total,tx_CustID,V12,tx_Region,$L$5,tx_Category,$M$5) -> 3509.9 | Y12: =RANK(X12,$X$4:$X$53,0)+COUNTIF($X$4:X12,X12)-1 -> 32
B13: Total Revenue | C13: =SUM(tx_Total) -> 229192.47 | D13: =What_If!B27 -> 250000 | E13: =C13/D13 -> 0.91676988 | H13: =Lists!A4 -> Central | I13: =SUMIFS(tx_Total,tx_Region,H13,tx_Category,$M$5) -> 41288.34 | J13: =IF(SUM($I$13:$I$17)=0,0,I13/SUM($I$13:$I$17)) -> 0.18014702 | K13: =IF(AVERAGE($I$13:$I$17)=0,0,I13/AVERAGE($I$13:$I$17)-1) -> -0.09926491 | P13: =Pivot_Summaries!Q14 -> Jan-25 | Q13: =SUMIFS(tx_Total,tx_Date,">="&Pivot_Summaries!J14,tx_Date,"<="&Pivot_Summaries!K14,tx_Region,$L$5,tx_Category,$M$5) -> 25799.15 | S13: =Lists!D13 -> Keyboard | T13: =SUMIFS(tx_Total,tx_Product,S13,tx_Region,$L$5,tx_Category,$M$5) -> 8009.11 | V13: =Lists!G13 -> CUST010 | W13: =Lists!H13 -> Maria Garcia | X13: =SUMIFS(tx_Total,tx_CustID,V13,tx_Region,$L$5,tx_Category,$M$5) -> 1909.93 | Y13: =RANK(X13,$X$4:$X$53,0)+COUNTIF($X$4:X13,X13)-1 -> 38
B14: Transactions | C14: =COUNTA(tx_ID) -> 250 | D14: 275 | E14: =C14/D14 -> 0.90909091 | H14: =Lists!A5 -> East | I14: =SUMIFS(tx_Total,tx_Region,H14,tx_Category,$M$5) -> 59288.39 | J14: =IF(SUM($I$13:$I$17)=0,0,I14/SUM($I$13:$I$17)) -> 0.25868385 | K14: =IF(AVERAGE($I$13:$I$17)=0,0,I14/AVERAGE($I$13:$I$17)-1) -> 0.29341924 | P14: =Pivot_Summaries!Q15 -> Feb-25 | Q14: =SUMIFS(tx_Total,tx_Date,">="&Pivot_Summaries!J15,tx_Date,"<="&Pivot_Summaries!K15,tx_Region,$L$5,tx_Category,$M$5) -> 16069.38 | V14: =Lists!G14 -> CUST011 | W14: =Lists!H14 -> William White | X14: =SUMIFS(tx_Total,tx_CustID,V14,tx_Region,$L$5,tx_Category,$M$5) -> 4749.91 | Y14: =RANK(X14,$X$4:$X$53,0)+COUNTIF($X$4:X14,X14)-1 -> 23
B15: Units Sold | C15: =SUM(tx_Qty) -> 753 | D15: 800 | E15: =C15/D15 -> 0.94125 | H15: =Lists!A6 -> North | I15: =SUMIFS(tx_Total,tx_Region,H15,tx_Category,$M$5) -> 50808.31 | J15: =IF(SUM($I$13:$I$17)=0,0,I15/SUM($I$13:$I$17)) -> 0.22168403 | K15: =IF(AVERAGE($I$13:$I$17)=0,0,I15/AVERAGE($I$13:$I$17)-1) -> 0.10842014 | P15: =Pivot_Summaries!Q16 -> Mar-25 | Q15: =SUMIFS(tx_Total,tx_Date,">="&Pivot_Summaries!J16,tx_Date,"<="&Pivot_Summaries!K16,tx_Region,$L$5,tx_Category,$M$5) -> 19899.38 | V15: =Lists!G15 -> CUST012 | W15: =Lists!H15 -> Patricia Moore | X15: =SUMIFS(tx_Total,tx_CustID,V15,tx_Region,$L$5,tx_Category,$M$5) -> 9799.73 | Y15: =RANK(X15,$X$4:$X$53,0)+COUNTIF($X$4:X15,X15)-1 -> 4
B16: Avg Order Value | C16: =C13/C14 -> 916.76988 | D16: 950 | E16: =C16/D16 -> 0.96502093 | H16: =Lists!A7 -> South | I16: =SUMIFS(tx_Total,tx_Region,H16,tx_Category,$M$5) -> 36398.75 | J16: =IF(SUM($I$13:$I$17)=0,0,I16/SUM($I$13:$I$17)) -> 0.15881303 | K16: =IF(AVERAGE($I$13:$I$17)=0,0,I16/AVERAGE($I$13:$I$17)-1) -> -0.20593486 | P16: =Pivot_Summaries!Q17 -> Apr-25 | Q16: =SUMIFS(tx_Total,tx_Date,">="&Pivot_Summaries!J17,tx_Date,"<="&Pivot_Summaries!K17,tx_Region,$L$5,tx_Category,$M$5) -> 6979.83 | V16: =Lists!G16 -> CUST013 | W16: =Lists!H16 -> Joseph Jackson | X16: =SUMIFS(tx_Total,tx_CustID,V16,tx_Region,$L$5,tx_Category,$M$5) -> 6949.84 | Y16: =RANK(X16,$X$4:$X$53,0)+COUNTIF($X$4:X16,X16)-1 -> 10
H17: =Lists!A8 -> West | I17: =SUMIFS(tx_Total,tx_Region,H17,tx_Category,$M$5) -> 41408.68 | J17: =IF(SUM($I$13:$I$17)=0,0,I17/SUM($I$13:$I$17)) -> 0.18067208 | K17: =IF(AVERAGE($I$13:$I$17)=0,0,I17/AVERAGE($I$13:$I$17)-1) -> -0.096639606 | V17: =Lists!G17 -> CUST014 | W17: =Lists!H17 -> Linda Martin | X17: =SUMIFS(tx_Total,tx_CustID,V17,tx_Region,$L$5,tx_Category,$M$5) -> 1289.9 | Y17: =RANK(X17,$X$4:$X$53,0)+COUNTIF($X$4:X17,X17)-1 -> 43
V18: =Lists!G18 -> CUST015 | W18: =Lists!H18 -> Richard Lee | X18: =SUMIFS(tx_Total,tx_CustID,V18,tx_Region,$L$5,tx_Category,$M$5) -> 739.93 | Y18: =RANK(X18,$X$4:$X$53,0)+COUNTIF($X$4:X18,X18)-1 -> 46
B19: Top 5 Customers | H19: Revenue by Category | V19: =Lists!G19 -> CUST016 | W19: =Lists!H19 -> Elizabeth Hall | X19: =SUMIFS(tx_Total,tx_CustID,V19,tx_Region,$L$5,tx_Category,$M$5) -> 3649.86 | Y19: =RANK(X19,$X$4:$X$53,0)+COUNTIF($X$4:X19,X19)-1 -> 31
B20: Rank | C20: Customer | D20: Revenue | E20: Share | H20: Category | I20: Revenue | J20: Share | V20: =Lists!G20 -> CUST017 | W20: =Lists!H20 -> Charles Allen | X20: =SUMIFS(tx_Total,tx_CustID,V20,tx_Region,$L$5,tx_Category,$M$5) -> 5089.73 | Y20: =RANK(X20,$X$4:$X$53,0)+COUNTIF($X$4:X20,X20)-1 -> 20
B21: 1 | C21: =IF(D21=0,"–",INDEX($W$4:$W$53,MATCH(B21,$Y$4:$Y$53,0))) -> Mark Carter | D21: =INDEX($X$4:$X$53,MATCH(B21,$Y$4:$Y$53,0)) -> 15659.65 | E21: =IF($B$8=0,0,D21/$B$8) -> 0.068325325 | H21: =Lists!B4 -> Appliances | I21: =SUMIFS(tx_Total,tx_Category,H21,tx_Region,$L$5) -> 8338.74 | J21: =IF(SUM($I$21:$I$23)=0,0,I21/SUM($I$21:$I$23)) -> 0.036383132 | V21: =Lists!G21 -> CUST018 | W21: =Lists!H21 -> Barbara Young | X21: =SUMIFS(tx_Total,tx_CustID,V21,tx_Region,$L$5,tx_Category,$M$5) -> 10649.8 | Y21: =RANK(X21,$X$4:$X$53,0)+COUNTIF($X$4:X21,X21)-1 -> 3
B22: 2 | C22: =IF(D22=0,"–",INDEX($W$4:$W$53,MATCH(B22,$Y$4:$Y$53,0))) -> Edward Mitchell | D22: =INDEX($X$4:$X$53,MATCH(B22,$Y$4:$Y$53,0)) -> 11919.77 | E22: =IF($B$8=0,0,D22/$B$8) -> 0.052007686 | H22: =Lists!B5 -> Electronics | I22: =SUMIFS(tx_Total,tx_Category,H22,tx_Region,$L$5) -> 171756.05 | J22: =IF(SUM($I$21:$I$23)=0,0,I22/SUM($I$21:$I$23)) -> 0.74939657 | V22: =Lists!G22 -> CUST019 | W22: =Lists!H22 -> Daniel King | X22: =SUMIFS(tx_Total,tx_CustID,V22,tx_Region,$L$5,tx_Category,$M$5) -> 7309.8 | Y22: =RANK(X22,$X$4:$X$53,0)+COUNTIF($X$4:X22,X22)-1 -> 8
B23: 3 | C23: =IF(D23=0,"–",INDEX($W$4:$W$53,MATCH(B23,$Y$4:$Y$53,0))) -> Barbara Young | D23: =INDEX($X$4:$X$53,MATCH(B23,$Y$4:$Y$53,0)) -> 10649.8 | E23: =IF($B$8=0,0,D23/$B$8) -> 0.046466623 | H23: =Lists!B6 -> Furniture | I23: =SUMIFS(tx_Total,tx_Category,H23,tx_Region,$L$5) -> 49097.68 | J23: =IF(SUM($I$21:$I$23)=0,0,I23/SUM($I$21:$I$23)) -> 0.2142203 | V23: =Lists!G23 -> CUST020 | W23: =Lists!H23 -> Margaret Wright | X23: =SUMIFS(tx_Total,tx_CustID,V23,tx_Region,$L$5,tx_Category,$M$5) -> 2099.88 | Y23: =RANK(X23,$X$4:$X$53,0)+COUNTIF($X$4:X23,X23)-1 -> 35
B24: 4 | C24: =IF(D24=0,"–",INDEX($W$4:$W$53,MATCH(B24,$Y$4:$Y$53,0))) -> Patricia Moore | D24: =INDEX($X$4:$X$53,MATCH(B24,$Y$4:$Y$53,0)) -> 9799.73 | E24: =IF($B$8=0,0,D24/$B$8) -> 0.042757644 | V24: =Lists!G24 -> CUST021 | W24: =Lists!H24 -> Kevin Scott | X24: =SUMIFS(tx_Total,tx_CustID,V24,tx_Region,$L$5,tx_Category,$M$5) -> 3259.87 | Y24: =RANK(X24,$X$4:$X$53,0)+COUNTIF($X$4:X24,X24)-1 -> 33
B25: 5 | C25: =IF(D25=0,"–",INDEX($W$4:$W$53,MATCH(B25,$Y$4:$Y$53,0))) -> Paul Baker | D25: =INDEX($X$4:$X$53,MATCH(B25,$Y$4:$Y$53,0)) -> 8309.74 | E25: =IF($B$8=0,0,D25/$B$8) -> 0.036256601 | V25: =Lists!G25 -> CUST022 | W25: =Lists!H25 -> Susan Green | X25: =SUMIFS(tx_Total,tx_CustID,V25,tx_Region,$L$5,tx_Category,$M$5) -> 1979.89 | Y25: =RANK(X25,$X$4:$X$53,0)+COUNTIF($X$4:X25,X25)-1 -> 37
V26: =Lists!G26 -> CUST023 | W26: =Lists!H26 -> Paul Baker | X26: =SUMIFS(tx_Total,tx_CustID,V26,tx_Region,$L$5,tx_Category,$M$5) -> 8309.74 | Y26: =RANK(X26,$X$4:$X$53,0)+COUNTIF($X$4:X26,X26)-1 -> 5
V27: =Lists!G27 -> CUST024 | W27: =Lists!H27 -> Dorothy Nelson | X27: =SUMIFS(tx_Total,tx_CustID,V27,tx_Region,$L$5,tx_Category,$M$5) -> 8269.79 | Y27: =RANK(X27,$X$4:$X$53,0)+COUNTIF($X$4:X27,X27)-1 -> 6
V28: =Lists!G28 -> CUST025 | W28: =Lists!H28 -> Mark Carter | X28: =SUMIFS(tx_Total,tx_CustID,V28,tx_Region,$L$5,tx_Category,$M$5) -> 15659.65 | Y28: =RANK(X28,$X$4:$X$53,0)+COUNTIF($X$4:X28,X28)-1 -> 1
V29: =Lists!G29 -> CUST026 | W29: =Lists!H29 -> Karen Hill | X29: =SUMIFS(tx_Total,tx_CustID,V29,tx_Region,$L$5,tx_Category,$M$5) -> 8009.77 | Y29: =RANK(X29,$X$4:$X$53,0)+COUNTIF($X$4:X29,X29)-1 -> 7
V30: =Lists!G30 -> CUST027 | W30: =Lists!H30 -> George Adams | X30: =SUMIFS(tx_Total,tx_CustID,V30,tx_Region,$L$5,tx_Category,$M$5) -> 3779.93 | Y30: =RANK(X30,$X$4:$X$53,0)+COUNTIF($X$4:X30,X30)-1 -> 28
V31: =Lists!G31 -> CUST028 | W31: =Lists!H31 -> Betty Campbell | X31: =SUMIFS(tx_Total,tx_CustID,V31,tx_Region,$L$5,tx_Category,$M$5) -> 5649.84 | Y31: =RANK(X31,$X$4:$X$53,0)+COUNTIF($X$4:X31,X31)-1 -> 16
V32: =Lists!G32 -> CUST029 | W32: =Lists!H32 -> Edward Mitchell | X32: =SUMIFS(tx_Total,tx_CustID,V32,tx_Region,$L$5,tx_Category,$M$5) -> 11919.77 | Y32: =RANK(X32,$X$4:$X$53,0)+COUNTIF($X$4:X32,X32)-1 -> 2
V33: =Lists!G33 -> CUST030 | W33: =Lists!H33 -> Helen Roberts | X33: =SUMIFS(tx_Total,tx_CustID,V33,tx_Region,$L$5,tx_Category,$M$5) -> 6459.79 | Y33: =RANK(X33,$X$4:$X$53,0)+COUNTIF($X$4:X33,X33)-1 -> 11
V34: =Lists!G34 -> CUST031 | W34: =Lists!H34 -> Steven Turner | X34: =SUMIFS(tx_Total,tx_CustID,V34,tx_Region,$L$5,tx_Category,$M$5) -> 2649.83 | Y34: =RANK(X34,$X$4:$X$53,0)+COUNTIF($X$4:X34,X34)-1 -> 34
V35: =Lists!G35 -> CUST032 | W35: =Lists!H35 -> Sandra Phillips | X35: =SUMIFS(tx_Total,tx_CustID,V35,tx_Region,$L$5,tx_Category,$M$5) -> 6349.83 | Y35: =RANK(X35,$X$4:$X$53,0)+COUNTIF($X$4:X35,X35)-1 -> 13
V36: =Lists!G36 -> CUST033 | W36: =Lists!H36 -> Frank Torres | X36: =SUMIFS(tx_Total,tx_CustID,V36,tx_Region,$L$5,tx_Category,$M$5) -> 1479.91 | Y36: =RANK(X36,$X$4:$X$53,0)+COUNTIF($X$4:X36,X36)-1 -> 42
V37: =Lists!G37 -> CUST034 | W37: =Lists!H37 -> Carol Evans | X37: =SUMIFS(tx_Total,tx_CustID,V37,tx_Region,$L$5,tx_Category,$M$5) -> 1149.93 | Y37: =RANK(X37,$X$4:$X$53,0)+COUNTIF($X$4:X37,X37)-1 -> 45
... V53: =Lists!G53 -> CUST050 | W53: =Lists!H53 -> Julie Foster | X53: =SUMIFS(tx_Total,tx_CustID,V53,tx_Region,$L$5,tx_Category,$M$5) -> 239.96 | Y53: =RANK(X53,$X$4:$X$53,0)+COUNTIF($X$4:X53,X53)-1 -> 49

Sheet Final_Report
B2: Key metrics
B3: Total Revenue | C3: =SUM(tx_Total) -> 229192.47
B4: Transactions | C4: =COUNTA(tx_ID) -> 250
B5: Units Sold | C5: =SUM(tx_Qty) -> 753
B6: Average Order Value | C6: =C3/C4 -> 916.76988
B7: Active Customers | C7: =COUNTIF(Customer_Analysis!C8:C57,">0") -> 50
B8: Average Revenue per Customer | C8: =C3/C7 -> 4583.8494
B10: Top customers
B11: Customer | C11: Revenue | D11: Share of revenue | E11: Transactions | F11: Tier
B12: =Customer_Analysis!O8 -> Mark Carter | C12: =Customer_Analysis!P8 -> 15659.65 | D12: =Customer_Analysis!Q8 -> 0.068325325 | E12: =Customer_Analysis!R8 -> 12 | F12: =Customer_Analysis!S8 -> High-Value
B13: =Customer_Analysis!O9 -> Edward Mitchell | C13: =Customer_Analysis!P9 -> 11919.77 | D13: =Customer_Analysis!Q9 -> 0.052007686 | E13: =Customer_Analysis!R9 -> 6 | F13: =Customer_Analysis!S9 -> High-Value
B14: =Customer_Analysis!O10 -> Barbara Young | C14: =Customer_Analysis!P10 -> 10649.8 | D14: =Customer_Analysis!Q10 -> 0.046466623 | E14: =Customer_Analysis!R10 -> 5 | F14: =Customer_Analysis!S10 -> High-Value
B15: =Customer_Analysis!O11 -> Patricia Moore | C15: =Customer_Analysis!P11 -> 9799.73 | D15: =Customer_Analysis!Q11 -> 0.042757644 | E15: =Customer_Analysis!R11 -> 8 | F15: =Customer_Analysis!S11 -> High-Value
B16: =Customer_Analysis!O12 -> Paul Baker | C16: =Customer_Analysis!P12 -> 8309.74 | D16: =Customer_Analysis!Q12 -> 0.036256601 | E16: =Customer_Analysis!R12 -> 8 | F16: =Customer_Analysis!S12 -> High-Value
B18: Most sold products
B19: Product | C19: Units | D19: Revenue | E19: Times purchased
B20: =Product_Analysis!N6 -> Bookshelf | C20: =Product_Analysis!O6 -> 102 | D20: =Product_Analysis!P6 -> 15298.98 | E20: =Product_Analysis!Q6 -> 35
B21: =Product_Analysis!N7 -> Smartphone | C21: =Product_Analysis!O7 -> 96 | D21: =Product_Analysis!P7 -> 67199.04 | E21: =Product_Analysis!Q7 -> 31
B22: =Product_Analysis!N8 -> Keyboard | C22: =Product_Analysis!O8 -> 89 | D22: =Product_Analysis!P8 -> 8009.11 | E22: =Product_Analysis!Q8 -> 34
B23: =Product_Analysis!N9 -> Monitor | C23: =Product_Analysis!O9 -> 88 | D23: =Product_Analysis!P9 -> 21999.12 | E23: =Product_Analysis!Q9 -> 26
B24: =Product_Analysis!N10 -> Blender | C24: =Product_Analysis!O10 -> 87 | D24: =Product_Analysis!P10 -> 5219.13 | E24: =Product_Analysis!Q10 -> 29
B26: Regional sales
B27: Region | C27: Revenue | D27: Share | E27: Transactions | F27: Avg Order Value
B28: =Pivot_Summaries!A15 -> Central | C28: =Pivot_Summaries!B15 -> 41288.34 | D28: =Pivot_Summaries!F15 -> 0.18014702 | E28: =Pivot_Summaries!C15 -> 54 | F28: =Pivot_Summaries!E15 -> 764.59889
B29: =Pivot_Summaries!A16 -> East | C29: =Pivot_Summaries!B16 -> 59288.39 | D29: =Pivot_Summaries!F16 -> 0.25868385 | E29: =Pivot_Summaries!C16 -> 48 | F29: =Pivot_Summaries!E16 -> 1235.1748
B30: =Pivot_Summaries!A17 -> North | C30: =Pivot_Summaries!B17 -> 50808.31 | D30: =Pivot_Summaries!F17 -> 0.22168403 | E30: =Pivot_Summaries!C17 -> 59 | F30: =Pivot_Summaries!E17 -> 861.1578
B31: =Pivot_Summaries!A18 -> South | C31: =Pivot_Summaries!B18 -> 36398.75 | D31: =Pivot_Summaries!F18 -> 0.15881303 | E31: =Pivot_Summaries!C18 -> 42 | F31: =Pivot_Summaries!E18 -> 866.6369
B32: =Pivot_Summaries!A19 -> West | C32: =Pivot_Summaries!B19 -> 41408.68 | D32: =Pivot_Summaries!F19 -> 0.18067208 | E32: =Pivot_Summaries!C19 -> 47 | F32: =Pivot_Summaries!E19 -> 881.03574
